/*      */ package org.apache.el.parser;
/*      */ 
/*      */ import java.util.List;
/*      */ 
/*      */ public class ELParser implements ELParserTreeConstants, ELParserConstants
/*      */ {
/*    7 */   protected JJTELParserState jjtree = new JJTELParserState();
/*      */   public ELParserTokenManager token_source;
/*      */   
/*   10 */   public static Node parse(String ref) throws javax.el.ELException { try { return new ELParser(new java.io.StringReader(ref)).CompositeExpression();
/*      */     } catch (ParseException pe) {
/*   12 */       throw new javax.el.ELException(pe.getMessage());
/*      */     }
/*      */   }
/*      */   
/*      */ 
/*      */ 
/*      */ 
/*      */ 
/*      */   public final AstCompositeExpression CompositeExpression()
/*      */     throws ParseException
/*      */   {
/*   23 */     AstCompositeExpression jjtn000 = new AstCompositeExpression(0);
/*   24 */     boolean jjtc000 = true;
/*   25 */     this.jjtree.openNodeScope(jjtn000);
/*      */     try
/*      */     {
/*      */       for (;;) {
/*   29 */         switch (this.jj_ntk == -1 ? jj_ntk() : this.jj_ntk)
/*      */         {
/*      */         case 1: 
/*      */         case 2: 
/*      */         case 3: 
/*      */           break;
/*      */         default: 
/*   36 */           this.jj_la1[0] = this.jj_gen;
/*   37 */           break;
/*      */         }
/*   39 */         switch (this.jj_ntk == -1 ? jj_ntk() : this.jj_ntk) {
/*      */         case 3: 
/*   41 */           DeferredExpression();
/*   42 */           break;
/*      */         case 2: 
/*   44 */           DynamicExpression();
/*   45 */           break;
/*      */         case 1: 
/*   47 */           LiteralExpression();
/*      */         }
/*      */       }
/*   50 */       this.jj_la1[1] = this.jj_gen;
/*   51 */       jj_consume_token(-1);
/*   52 */       throw new ParseException();
/*      */       
/*      */ 
/*   55 */       jj_consume_token(0);
/*   56 */       this.jjtree.closeNodeScope(jjtn000, true);
/*   57 */       jjtc000 = false;
/*   58 */       return jjtn000;
/*      */     } catch (Throwable jjte000) {
/*   60 */       if (jjtc000) {
/*   61 */         this.jjtree.clearNodeScope(jjtn000);
/*   62 */         jjtc000 = false;
/*      */       } else {
/*   64 */         this.jjtree.popNode();
/*      */       }
/*   66 */       if ((jjte000 instanceof RuntimeException)) {
/*   67 */         throw ((RuntimeException)jjte000);
/*      */       }
/*   69 */       if ((jjte000 instanceof ParseException)) {
/*   70 */         throw ((ParseException)jjte000);
/*      */       }
/*   72 */       throw ((Error)jjte000);
/*      */     } finally {
/*   74 */       if (jjtc000) {
/*   75 */         this.jjtree.closeNodeScope(jjtn000, true);
/*      */       }
/*      */     }
/*      */   }
/*      */   
/*      */ 
/*      */ 
/*      */ 
/*      */ 
/*      */   public final void LiteralExpression()
/*      */     throws ParseException
/*      */   {
/*   87 */     AstLiteralExpression jjtn000 = new AstLiteralExpression(1);
/*   88 */     boolean jjtc000 = true;
/*   89 */     this.jjtree.openNodeScope(jjtn000);Token t = null;
/*      */     try {
/*   91 */       t = jj_consume_token(1);
/*   92 */       this.jjtree.closeNodeScope(jjtn000, true);
/*   93 */       jjtc000 = false;
/*   94 */       jjtn000.setImage(t.image);
/*      */     } finally {
/*   96 */       if (jjtc000) {
/*   97 */         this.jjtree.closeNodeScope(jjtn000, true);
/*      */       }
/*      */     }
/*      */   }
/*      */   
/*      */ 
/*      */ 
/*      */ 
/*      */   public final void DeferredExpression()
/*      */     throws ParseException
/*      */   {
/*  108 */     AstDeferredExpression jjtn000 = new AstDeferredExpression(2);
/*  109 */     boolean jjtc000 = true;
/*  110 */     this.jjtree.openNodeScope(jjtn000);
/*      */     try {
/*  112 */       jj_consume_token(3);
/*  113 */       Expression();
/*  114 */       jj_consume_token(9);
/*      */     } catch (Throwable jjte000) {
/*  116 */       if (jjtc000) {
/*  117 */         this.jjtree.clearNodeScope(jjtn000);
/*  118 */         jjtc000 = false;
/*      */       } else {
/*  120 */         this.jjtree.popNode();
/*      */       }
/*  122 */       if ((jjte000 instanceof RuntimeException)) {
/*  123 */         throw ((RuntimeException)jjte000);
/*      */       }
/*  125 */       if ((jjte000 instanceof ParseException)) {
/*  126 */         throw ((ParseException)jjte000);
/*      */       }
/*  128 */       throw ((Error)jjte000);
/*      */     } finally {
/*  130 */       if (jjtc000) {
/*  131 */         this.jjtree.closeNodeScope(jjtn000, true);
/*      */       }
/*      */     }
/*      */   }
/*      */   
/*      */ 
/*      */ 
/*      */ 
/*      */   public final void DynamicExpression()
/*      */     throws ParseException
/*      */   {
/*  142 */     AstDynamicExpression jjtn000 = new AstDynamicExpression(3);
/*  143 */     boolean jjtc000 = true;
/*  144 */     this.jjtree.openNodeScope(jjtn000);
/*      */     try {
/*  146 */       jj_consume_token(2);
/*  147 */       Expression();
/*  148 */       jj_consume_token(9);
/*      */     } catch (Throwable jjte000) {
/*  150 */       if (jjtc000) {
/*  151 */         this.jjtree.clearNodeScope(jjtn000);
/*  152 */         jjtc000 = false;
/*      */       } else {
/*  154 */         this.jjtree.popNode();
/*      */       }
/*  156 */       if ((jjte000 instanceof RuntimeException)) {
/*  157 */         throw ((RuntimeException)jjte000);
/*      */       }
/*  159 */       if ((jjte000 instanceof ParseException)) {
/*  160 */         throw ((ParseException)jjte000);
/*      */       }
/*  162 */       throw ((Error)jjte000);
/*      */     } finally {
/*  164 */       if (jjtc000) {
/*  165 */         this.jjtree.closeNodeScope(jjtn000, true);
/*      */       }
/*      */     }
/*      */   }
/*      */   
/*      */ 
/*      */ 
/*      */   public final void Expression()
/*      */     throws ParseException
/*      */   {
/*  175 */     Semicolon();
/*      */   }
/*      */   
/*      */ 
/*      */   public final void Semicolon()
/*      */     throws ParseException
/*      */   {
/*  182 */     Assignment();
/*      */     for (;;)
/*      */     {
/*  185 */       switch (this.jj_ntk == -1 ? jj_ntk() : this.jj_ntk)
/*      */       {
/*      */       case 23: 
/*      */         break;
/*      */       default: 
/*  190 */         this.jj_la1[2] = this.jj_gen;
/*  191 */         break;
/*      */       }
/*  193 */       jj_consume_token(23);
/*  194 */       AstSemicolon jjtn001 = new AstSemicolon(5);
/*  195 */       boolean jjtc001 = true;
/*  196 */       this.jjtree.openNodeScope(jjtn001);
/*      */       try {
/*  198 */         Assignment();
/*      */       } catch (Throwable jjte001) {
/*  200 */         if (jjtc001) {
/*  201 */           this.jjtree.clearNodeScope(jjtn001);
/*  202 */           jjtc001 = false;
/*      */         } else {
/*  204 */           this.jjtree.popNode();
/*      */         }
/*  206 */         if ((jjte001 instanceof RuntimeException)) {
/*  207 */           throw ((RuntimeException)jjte001);
/*      */         }
/*  209 */         if ((jjte001 instanceof ParseException)) {
/*  210 */           throw ((ParseException)jjte001);
/*      */         }
/*  212 */         throw ((Error)jjte001);
/*      */       } finally {
/*  214 */         if (jjtc001) {
/*  215 */           this.jjtree.closeNodeScope(jjtn001, 2);
/*      */         }
/*      */       }
/*      */     }
/*      */   }
/*      */   
/*      */ 
/*      */   public final void Assignment()
/*      */     throws ParseException
/*      */   {
/*  225 */     if (jj_2_2(4)) {
/*  226 */       LambdaExpression();
/*      */     } else {
/*  228 */       switch (this.jj_ntk == -1 ? jj_ntk() : this.jj_ntk) {
/*      */       case 8: 
/*      */       case 10: 
/*      */       case 11: 
/*      */       case 13: 
/*      */       case 14: 
/*      */       case 15: 
/*      */       case 16: 
/*      */       case 18: 
/*      */       case 20: 
/*      */       case 37: 
/*      */       case 38: 
/*      */       case 43: 
/*      */       case 47: 
/*      */       case 56: 
/*  243 */         Choice();
/*      */       }
/*      */       
/*  246 */       while (jj_2_1(2))
/*      */       {
/*      */ 
/*      */ 
/*      */ 
/*  251 */         jj_consume_token(54);
/*  252 */         AstAssign jjtn001 = new AstAssign(6);
/*  253 */         boolean jjtc001 = true;
/*  254 */         this.jjtree.openNodeScope(jjtn001);
/*      */         try {
/*  256 */           Assignment();
/*      */         } catch (Throwable jjte001) {
/*  258 */           if (jjtc001) {
/*  259 */             this.jjtree.clearNodeScope(jjtn001);
/*  260 */             jjtc001 = false;
/*      */           } else {
/*  262 */             this.jjtree.popNode();
/*      */           }
/*  264 */           if ((jjte001 instanceof RuntimeException)) {
/*  265 */             throw ((RuntimeException)jjte001);
/*      */           }
/*  267 */           if ((jjte001 instanceof ParseException)) {
/*  268 */             throw ((ParseException)jjte001);
/*      */           }
/*  270 */           throw ((Error)jjte001);
/*      */         } finally {
/*  272 */           if (jjtc001) {
/*  273 */             this.jjtree.closeNodeScope(jjtn001, 2);
/*      */           }
/*      */         }
/*  276 */         continue;
/*      */         
/*      */ 
/*  279 */         this.jj_la1[3] = this.jj_gen;
/*  280 */         jj_consume_token(-1);
/*  281 */         throw new ParseException();
/*      */       }
/*      */     }
/*      */   }
/*      */   
/*      */ 
/*      */ 
/*      */   public final void LambdaExpression()
/*      */     throws ParseException
/*      */   {
/*  291 */     AstLambdaExpression jjtn000 = new AstLambdaExpression(7);
/*  292 */     boolean jjtc000 = true;
/*  293 */     this.jjtree.openNodeScope(jjtn000);
/*      */     try {
/*  295 */       LambdaParameters();
/*  296 */       jj_consume_token(55);
/*  297 */       if (jj_2_3(3)) {
/*  298 */         LambdaExpression();
/*      */       } else {
/*  300 */         switch (this.jj_ntk == -1 ? jj_ntk() : this.jj_ntk) {
/*      */         case 8: 
/*      */         case 10: 
/*      */         case 11: 
/*      */         case 13: 
/*      */         case 14: 
/*      */         case 15: 
/*      */         case 16: 
/*      */         case 18: 
/*      */         case 20: 
/*      */         case 37: 
/*      */         case 38: 
/*      */         case 43: 
/*      */         case 47: 
/*      */         case 56: 
/*  315 */           Choice();
/*  316 */           break;
/*      */         case 9: case 12: case 17: case 19: case 21: case 22: case 23: case 24: case 25: case 26: case 27: case 28: case 29: case 30: case 31: case 32: case 33: case 34: case 35: case 36: case 39: case 40: case 41: case 42: case 44: case 45: case 46: case 48: case 49: case 50: case 51: case 52: case 53: case 54: case 55: default: 
/*  318 */           this.jj_la1[4] = this.jj_gen;
/*  319 */           jj_consume_token(-1);
/*  320 */           throw new ParseException();
/*      */         }
/*      */       }
/*      */     } catch (Throwable jjte000) {
/*  324 */       if (jjtc000) {
/*  325 */         this.jjtree.clearNodeScope(jjtn000);
/*  326 */         jjtc000 = false;
/*      */       } else {
/*  328 */         this.jjtree.popNode();
/*      */       }
/*  330 */       if ((jjte000 instanceof RuntimeException)) {
/*  331 */         throw ((RuntimeException)jjte000);
/*      */       }
/*  333 */       if ((jjte000 instanceof ParseException)) {
/*  334 */         throw ((ParseException)jjte000);
/*      */       }
/*  336 */       throw ((Error)jjte000);
/*      */     } finally {
/*  338 */       if (jjtc000) {
/*  339 */         this.jjtree.closeNodeScope(jjtn000, true);
/*      */       }
/*      */     }
/*      */   }
/*      */   
/*      */ 
/*      */ 
/*      */   public final void LambdaParameters()
/*      */     throws ParseException
/*      */   {
/*  349 */     AstLambdaParameters jjtn000 = new AstLambdaParameters(8);
/*  350 */     boolean jjtc000 = true;
/*  351 */     this.jjtree.openNodeScope(jjtn000);
/*      */     try {
/*  353 */       switch (this.jj_ntk == -1 ? jj_ntk() : this.jj_ntk) {
/*      */       case 56: 
/*  355 */         Identifier();
/*  356 */         break;
/*      */       case 18: 
/*  358 */         jj_consume_token(18);
/*  359 */         switch (this.jj_ntk == -1 ? jj_ntk() : this.jj_ntk) {
/*      */         case 56: 
/*  361 */           Identifier();
/*      */           for (;;)
/*      */           {
/*  364 */             switch (this.jj_ntk == -1 ? jj_ntk() : this.jj_ntk)
/*      */             {
/*      */             case 24: 
/*      */               break;
/*      */             default: 
/*  369 */               this.jj_la1[5] = this.jj_gen;
/*  370 */               break;
/*      */             }
/*  372 */             jj_consume_token(24);
/*  373 */             Identifier();
/*      */           }
/*      */         }
/*      */         
/*  377 */         this.jj_la1[6] = this.jj_gen;
/*      */         
/*      */ 
/*  380 */         jj_consume_token(19);
/*  381 */         break;
/*      */       default: 
/*  383 */         this.jj_la1[7] = this.jj_gen;
/*  384 */         jj_consume_token(-1);
/*  385 */         throw new ParseException();
/*      */       }
/*      */     } catch (Throwable jjte000) {
/*  388 */       if (jjtc000) {
/*  389 */         this.jjtree.clearNodeScope(jjtn000);
/*  390 */         jjtc000 = false;
/*      */       } else {
/*  392 */         this.jjtree.popNode();
/*      */       }
/*  394 */       if ((jjte000 instanceof RuntimeException)) {
/*  395 */         throw ((RuntimeException)jjte000);
/*      */       }
/*  397 */       if ((jjte000 instanceof ParseException)) {
/*  398 */         throw ((ParseException)jjte000);
/*      */       }
/*  400 */       throw ((Error)jjte000);
/*      */     } finally {
/*  402 */       if (jjtc000) {
/*  403 */         this.jjtree.closeNodeScope(jjtn000, true);
/*      */       }
/*      */     }
/*      */   }
/*      */   
/*      */ 
/*      */ 
/*      */ 
/*      */   public final void LambdaExpressionOrInvocation()
/*      */     throws ParseException
/*      */   {
/*  414 */     AstLambdaExpression jjtn000 = new AstLambdaExpression(7);
/*  415 */     boolean jjtc000 = true;
/*  416 */     this.jjtree.openNodeScope(jjtn000);
/*      */     try {
/*  418 */       jj_consume_token(18);
/*  419 */       LambdaParameters();
/*  420 */       jj_consume_token(55);
/*  421 */       if (jj_2_4(3)) {
/*  422 */         LambdaExpression();
/*      */       } else {
/*  424 */         switch (this.jj_ntk == -1 ? jj_ntk() : this.jj_ntk) {
/*      */         case 8: 
/*      */         case 10: 
/*      */         case 11: 
/*      */         case 13: 
/*      */         case 14: 
/*      */         case 15: 
/*      */         case 16: 
/*      */         case 18: 
/*      */         case 20: 
/*      */         case 37: 
/*      */         case 38: 
/*      */         case 43: 
/*      */         case 47: 
/*      */         case 56: 
/*  439 */           Choice();
/*  440 */           break;
/*      */         case 9: case 12: case 17: case 19: case 21: case 22: case 23: case 24: case 25: case 26: case 27: case 28: case 29: case 30: case 31: case 32: case 33: case 34: case 35: case 36: case 39: case 40: case 41: case 42: case 44: case 45: case 46: case 48: case 49: case 50: case 51: case 52: case 53: case 54: case 55: default: 
/*  442 */           this.jj_la1[8] = this.jj_gen;
/*  443 */           jj_consume_token(-1);
/*  444 */           throw new ParseException();
/*      */         }
/*      */       }
/*  447 */       jj_consume_token(19);
/*      */       for (;;)
/*      */       {
/*  450 */         switch (this.jj_ntk == -1 ? jj_ntk() : this.jj_ntk)
/*      */         {
/*      */         case 18: 
/*      */           break;
/*      */         default: 
/*  455 */           this.jj_la1[9] = this.jj_gen;
/*  456 */           break;
/*      */         }
/*  458 */         MethodParameters();
/*      */       }
/*      */     } catch (Throwable jjte000) {
/*  461 */       if (jjtc000) {
/*  462 */         this.jjtree.clearNodeScope(jjtn000);
/*  463 */         jjtc000 = false;
/*      */       } else {
/*  465 */         this.jjtree.popNode();
/*      */       }
/*  467 */       if ((jjte000 instanceof RuntimeException)) {
/*  468 */         throw ((RuntimeException)jjte000);
/*      */       }
/*  470 */       if ((jjte000 instanceof ParseException)) {
/*  471 */         throw ((ParseException)jjte000);
/*      */       }
/*  473 */       throw ((Error)jjte000);
/*      */     } finally {
/*  475 */       if (jjtc000) {
/*  476 */         this.jjtree.closeNodeScope(jjtn000, true);
/*      */       }
/*      */     }
/*      */   }
/*      */   
/*      */ 
/*      */ 
/*      */   public final void Choice()
/*      */     throws ParseException
/*      */   {
/*  486 */     Or();
/*      */     
/*      */ 
/*  489 */     while (jj_2_5(3))
/*      */     {
/*      */ 
/*      */ 
/*      */ 
/*  494 */       jj_consume_token(48);
/*  495 */       Choice();
/*  496 */       jj_consume_token(22);
/*  497 */       AstChoice jjtn001 = new AstChoice(9);
/*  498 */       boolean jjtc001 = true;
/*  499 */       this.jjtree.openNodeScope(jjtn001);
/*      */       try {
/*  501 */         Choice();
/*      */       } catch (Throwable jjte001) {
/*  503 */         if (jjtc001) {
/*  504 */           this.jjtree.clearNodeScope(jjtn001);
/*  505 */           jjtc001 = false;
/*      */         } else {
/*  507 */           this.jjtree.popNode();
/*      */         }
/*  509 */         if ((jjte001 instanceof RuntimeException)) {
/*  510 */           throw ((RuntimeException)jjte001);
/*      */         }
/*  512 */         if ((jjte001 instanceof ParseException)) {
/*  513 */           throw ((ParseException)jjte001);
/*      */         }
/*  515 */         throw ((Error)jjte001);
/*      */       } finally {
/*  517 */         if (jjtc001) {
/*  518 */           this.jjtree.closeNodeScope(jjtn001, 3);
/*      */         }
/*      */       }
/*      */     }
/*      */   }
/*      */   
/*      */ 
/*      */ 
/*      */   public final void Or()
/*      */     throws ParseException
/*      */   {
/*  529 */     And();
/*      */     for (;;)
/*      */     {
/*  532 */       switch (this.jj_ntk == -1 ? jj_ntk() : this.jj_ntk)
/*      */       {
/*      */       case 41: 
/*      */       case 42: 
/*      */         break;
/*      */       default: 
/*  538 */         this.jj_la1[10] = this.jj_gen;
/*  539 */         break;
/*      */       }
/*  541 */       switch (this.jj_ntk == -1 ? jj_ntk() : this.jj_ntk) {
/*      */       case 41: 
/*  543 */         jj_consume_token(41);
/*  544 */         break;
/*      */       case 42: 
/*  546 */         jj_consume_token(42);
/*  547 */         break;
/*      */       default: 
/*  549 */         this.jj_la1[11] = this.jj_gen;
/*  550 */         jj_consume_token(-1);
/*  551 */         throw new ParseException();
/*      */       }
/*  553 */       AstOr jjtn001 = new AstOr(10);
/*  554 */       boolean jjtc001 = true;
/*  555 */       this.jjtree.openNodeScope(jjtn001);
/*      */       try {
/*  557 */         And();
/*      */       } catch (Throwable jjte001) {
/*  559 */         if (jjtc001) {
/*  560 */           this.jjtree.clearNodeScope(jjtn001);
/*  561 */           jjtc001 = false;
/*      */         } else {
/*  563 */           this.jjtree.popNode();
/*      */         }
/*  565 */         if ((jjte001 instanceof RuntimeException)) {
/*  566 */           throw ((RuntimeException)jjte001);
/*      */         }
/*  568 */         if ((jjte001 instanceof ParseException)) {
/*  569 */           throw ((ParseException)jjte001);
/*      */         }
/*  571 */         throw ((Error)jjte001);
/*      */       } finally {
/*  573 */         if (jjtc001) {
/*  574 */           this.jjtree.closeNodeScope(jjtn001, 2);
/*      */         }
/*      */       }
/*      */     }
/*      */   }
/*      */   
/*      */ 
/*      */ 
/*      */   public final void And()
/*      */     throws ParseException
/*      */   {
/*  585 */     Equality();
/*      */     for (;;)
/*      */     {
/*  588 */       switch (this.jj_ntk == -1 ? jj_ntk() : this.jj_ntk)
/*      */       {
/*      */       case 39: 
/*      */       case 40: 
/*      */         break;
/*      */       default: 
/*  594 */         this.jj_la1[12] = this.jj_gen;
/*  595 */         break;
/*      */       }
/*  597 */       switch (this.jj_ntk == -1 ? jj_ntk() : this.jj_ntk) {
/*      */       case 39: 
/*  599 */         jj_consume_token(39);
/*  600 */         break;
/*      */       case 40: 
/*  602 */         jj_consume_token(40);
/*  603 */         break;
/*      */       default: 
/*  605 */         this.jj_la1[13] = this.jj_gen;
/*  606 */         jj_consume_token(-1);
/*  607 */         throw new ParseException();
/*      */       }
/*  609 */       AstAnd jjtn001 = new AstAnd(11);
/*  610 */       boolean jjtc001 = true;
/*  611 */       this.jjtree.openNodeScope(jjtn001);
/*      */       try {
/*  613 */         Equality();
/*      */       } catch (Throwable jjte001) {
/*  615 */         if (jjtc001) {
/*  616 */           this.jjtree.clearNodeScope(jjtn001);
/*  617 */           jjtc001 = false;
/*      */         } else {
/*  619 */           this.jjtree.popNode();
/*      */         }
/*  621 */         if ((jjte001 instanceof RuntimeException)) {
/*  622 */           throw ((RuntimeException)jjte001);
/*      */         }
/*  624 */         if ((jjte001 instanceof ParseException)) {
/*  625 */           throw ((ParseException)jjte001);
/*      */         }
/*  627 */         throw ((Error)jjte001);
/*      */       } finally {
/*  629 */         if (jjtc001) {
/*  630 */           this.jjtree.closeNodeScope(jjtn001, 2);
/*      */         }
/*      */       }
/*      */     }
/*      */   }
/*      */   
/*      */ 
/*      */ 
/*      */   public final void Equality()
/*      */     throws ParseException
/*      */   {
/*  641 */     Compare();
/*      */     for (;;)
/*      */     {
/*  644 */       switch (this.jj_ntk == -1 ? jj_ntk() : this.jj_ntk)
/*      */       {
/*      */       case 33: 
/*      */       case 34: 
/*      */       case 35: 
/*      */       case 36: 
/*      */         break;
/*      */       default: 
/*  652 */         this.jj_la1[14] = this.jj_gen;
/*  653 */         break;
/*      */       }
/*  655 */       switch (this.jj_ntk == -1 ? jj_ntk() : this.jj_ntk) {
/*      */       case 33: 
/*      */       case 34: 
/*  658 */         switch (this.jj_ntk == -1 ? jj_ntk() : this.jj_ntk) {
/*      */         case 33: 
/*  660 */           jj_consume_token(33);
/*  661 */           break;
/*      */         case 34: 
/*  663 */           jj_consume_token(34);
/*  664 */           break;
/*      */         default: 
/*  666 */           this.jj_la1[15] = this.jj_gen;
/*  667 */           jj_consume_token(-1);
/*  668 */           throw new ParseException();
/*      */         }
/*  670 */         AstEqual jjtn001 = new AstEqual(12);
/*  671 */         boolean jjtc001 = true;
/*  672 */         this.jjtree.openNodeScope(jjtn001);
/*      */         try {
/*  674 */           Compare();
/*      */         } catch (Throwable jjte001) {
/*  676 */           if (jjtc001) {
/*  677 */             this.jjtree.clearNodeScope(jjtn001);
/*  678 */             jjtc001 = false;
/*      */           } else {
/*  680 */             this.jjtree.popNode();
/*      */           }
/*  682 */           if ((jjte001 instanceof RuntimeException)) {
/*  683 */             throw ((RuntimeException)jjte001);
/*      */           }
/*  685 */           if ((jjte001 instanceof ParseException)) {
/*  686 */             throw ((ParseException)jjte001);
/*      */           }
/*  688 */           throw ((Error)jjte001);
/*      */         } finally {
/*  690 */           if (jjtc001) {
/*  691 */             this.jjtree.closeNodeScope(jjtn001, 2);
/*      */           }
/*      */         }
/*  694 */         break;
/*      */       case 35: 
/*      */       case 36: 
/*  697 */         switch (this.jj_ntk == -1 ? jj_ntk() : this.jj_ntk) {
/*      */         case 35: 
/*  699 */           jj_consume_token(35);
/*  700 */           break;
/*      */         case 36: 
/*  702 */           jj_consume_token(36);
/*  703 */           break;
/*      */         default: 
/*  705 */           this.jj_la1[16] = this.jj_gen;
/*  706 */           jj_consume_token(-1);
/*  707 */           throw new ParseException();
/*      */         }
/*  709 */         AstNotEqual jjtn002 = new AstNotEqual(13);
/*  710 */         boolean jjtc002 = true;
/*  711 */         this.jjtree.openNodeScope(jjtn002);
/*      */         try {
/*  713 */           Compare();
/*      */         } catch (Throwable jjte002) {
/*  715 */           if (jjtc002) {
/*  716 */             this.jjtree.clearNodeScope(jjtn002);
/*  717 */             jjtc002 = false;
/*      */           } else {
/*  719 */             this.jjtree.popNode();
/*      */           }
/*  721 */           if ((jjte002 instanceof RuntimeException)) {
/*  722 */             throw ((RuntimeException)jjte002);
/*      */           }
/*  724 */           if ((jjte002 instanceof ParseException)) {
/*  725 */             throw ((ParseException)jjte002);
/*      */           }
/*  727 */           throw ((Error)jjte002);
/*      */         } finally {
/*  729 */           if (jjtc002) {
/*  730 */             this.jjtree.closeNodeScope(jjtn002, 2);
/*      */           }
/*      */         }
/*      */       }
/*      */     }
/*  735 */     this.jj_la1[17] = this.jj_gen;
/*  736 */     jj_consume_token(-1);
/*  737 */     throw new ParseException();
/*      */   }
/*      */   
/*      */ 
/*      */ 
/*      */ 
/*      */ 
/*      */   public final void Compare()
/*      */     throws ParseException
/*      */   {
/*  747 */     Concatenation();
/*      */     for (;;)
/*      */     {
/*  750 */       switch (this.jj_ntk == -1 ? jj_ntk() : this.jj_ntk)
/*      */       {
/*      */       case 25: 
/*      */       case 26: 
/*      */       case 27: 
/*      */       case 28: 
/*      */       case 29: 
/*      */       case 30: 
/*      */       case 31: 
/*      */       case 32: 
/*      */         break;
/*      */       default: 
/*  762 */         this.jj_la1[18] = this.jj_gen;
/*  763 */         break;
/*      */       }
/*  765 */       switch (this.jj_ntk == -1 ? jj_ntk() : this.jj_ntk) {
/*      */       case 27: 
/*      */       case 28: 
/*  768 */         switch (this.jj_ntk == -1 ? jj_ntk() : this.jj_ntk) {
/*      */         case 27: 
/*  770 */           jj_consume_token(27);
/*  771 */           break;
/*      */         case 28: 
/*  773 */           jj_consume_token(28);
/*  774 */           break;
/*      */         default: 
/*  776 */           this.jj_la1[19] = this.jj_gen;
/*  777 */           jj_consume_token(-1);
/*  778 */           throw new ParseException();
/*      */         }
/*  780 */         AstLessThan jjtn001 = new AstLessThan(14);
/*  781 */         boolean jjtc001 = true;
/*  782 */         this.jjtree.openNodeScope(jjtn001);
/*      */         try {
/*  784 */           Concatenation();
/*      */         } catch (Throwable jjte001) {
/*  786 */           if (jjtc001) {
/*  787 */             this.jjtree.clearNodeScope(jjtn001);
/*  788 */             jjtc001 = false;
/*      */           } else {
/*  790 */             this.jjtree.popNode();
/*      */           }
/*  792 */           if ((jjte001 instanceof RuntimeException)) {
/*  793 */             throw ((RuntimeException)jjte001);
/*      */           }
/*  795 */           if ((jjte001 instanceof ParseException)) {
/*  796 */             throw ((ParseException)jjte001);
/*      */           }
/*  798 */           throw ((Error)jjte001);
/*      */         } finally {
/*  800 */           if (jjtc001) {
/*  801 */             this.jjtree.closeNodeScope(jjtn001, 2);
/*      */           }
/*      */         }
/*  804 */         break;
/*      */       case 25: 
/*      */       case 26: 
/*  807 */         switch (this.jj_ntk == -1 ? jj_ntk() : this.jj_ntk) {
/*      */         case 25: 
/*  809 */           jj_consume_token(25);
/*  810 */           break;
/*      */         case 26: 
/*  812 */           jj_consume_token(26);
/*  813 */           break;
/*      */         default: 
/*  815 */           this.jj_la1[20] = this.jj_gen;
/*  816 */           jj_consume_token(-1);
/*  817 */           throw new ParseException();
/*      */         }
/*  819 */         AstGreaterThan jjtn002 = new AstGreaterThan(15);
/*  820 */         boolean jjtc002 = true;
/*  821 */         this.jjtree.openNodeScope(jjtn002);
/*      */         try {
/*  823 */           Concatenation();
/*      */         } catch (Throwable jjte002) {
/*  825 */           if (jjtc002) {
/*  826 */             this.jjtree.clearNodeScope(jjtn002);
/*  827 */             jjtc002 = false;
/*      */           } else {
/*  829 */             this.jjtree.popNode();
/*      */           }
/*  831 */           if ((jjte002 instanceof RuntimeException)) {
/*  832 */             throw ((RuntimeException)jjte002);
/*      */           }
/*  834 */           if ((jjte002 instanceof ParseException)) {
/*  835 */             throw ((ParseException)jjte002);
/*      */           }
/*  837 */           throw ((Error)jjte002);
/*      */         } finally {
/*  839 */           if (jjtc002) {
/*  840 */             this.jjtree.closeNodeScope(jjtn002, 2);
/*      */           }
/*      */         }
/*  843 */         break;
/*      */       case 31: 
/*      */       case 32: 
/*  846 */         switch (this.jj_ntk == -1 ? jj_ntk() : this.jj_ntk) {
/*      */         case 31: 
/*  848 */           jj_consume_token(31);
/*  849 */           break;
/*      */         case 32: 
/*  851 */           jj_consume_token(32);
/*  852 */           break;
/*      */         default: 
/*  854 */           this.jj_la1[21] = this.jj_gen;
/*  855 */           jj_consume_token(-1);
/*  856 */           throw new ParseException();
/*      */         }
/*  858 */         AstLessThanEqual jjtn003 = new AstLessThanEqual(16);
/*  859 */         boolean jjtc003 = true;
/*  860 */         this.jjtree.openNodeScope(jjtn003);
/*      */         try {
/*  862 */           Concatenation();
/*      */         } catch (Throwable jjte003) {
/*  864 */           if (jjtc003) {
/*  865 */             this.jjtree.clearNodeScope(jjtn003);
/*  866 */             jjtc003 = false;
/*      */           } else {
/*  868 */             this.jjtree.popNode();
/*      */           }
/*  870 */           if ((jjte003 instanceof RuntimeException)) {
/*  871 */             throw ((RuntimeException)jjte003);
/*      */           }
/*  873 */           if ((jjte003 instanceof ParseException)) {
/*  874 */             throw ((ParseException)jjte003);
/*      */           }
/*  876 */           throw ((Error)jjte003);
/*      */         } finally {
/*  878 */           if (jjtc003) {
/*  879 */             this.jjtree.closeNodeScope(jjtn003, 2);
/*      */           }
/*      */         }
/*  882 */         break;
/*      */       case 29: 
/*      */       case 30: 
/*  885 */         switch (this.jj_ntk == -1 ? jj_ntk() : this.jj_ntk) {
/*      */         case 29: 
/*  887 */           jj_consume_token(29);
/*  888 */           break;
/*      */         case 30: 
/*  890 */           jj_consume_token(30);
/*  891 */           break;
/*      */         default: 
/*  893 */           this.jj_la1[22] = this.jj_gen;
/*  894 */           jj_consume_token(-1);
/*  895 */           throw new ParseException();
/*      */         }
/*  897 */         AstGreaterThanEqual jjtn004 = new AstGreaterThanEqual(17);
/*  898 */         boolean jjtc004 = true;
/*  899 */         this.jjtree.openNodeScope(jjtn004);
/*      */         try {
/*  901 */           Concatenation();
/*      */         } catch (Throwable jjte004) {
/*  903 */           if (jjtc004) {
/*  904 */             this.jjtree.clearNodeScope(jjtn004);
/*  905 */             jjtc004 = false;
/*      */           } else {
/*  907 */             this.jjtree.popNode();
/*      */           }
/*  909 */           if ((jjte004 instanceof RuntimeException)) {
/*  910 */             throw ((RuntimeException)jjte004);
/*      */           }
/*  912 */           if ((jjte004 instanceof ParseException)) {
/*  913 */             throw ((ParseException)jjte004);
/*      */           }
/*  915 */           throw ((Error)jjte004);
/*      */         } finally {
/*  917 */           if (jjtc004) {
/*  918 */             this.jjtree.closeNodeScope(jjtn004, 2);
/*      */           }
/*      */         }
/*      */       }
/*      */     }
/*  923 */     this.jj_la1[23] = this.jj_gen;
/*  924 */     jj_consume_token(-1);
/*  925 */     throw new ParseException();
/*      */   }
/*      */   
/*      */ 
/*      */ 
/*      */ 
/*      */ 
/*      */ 
/*      */   public final void Concatenation()
/*      */     throws ParseException
/*      */   {
/*  936 */     Math();
/*      */     for (;;)
/*      */     {
/*  939 */       switch (this.jj_ntk == -1 ? jj_ntk() : this.jj_ntk)
/*      */       {
/*      */       case 53: 
/*      */         break;
/*      */       default: 
/*  944 */         this.jj_la1[24] = this.jj_gen;
/*  945 */         break;
/*      */       }
/*  947 */       jj_consume_token(53);
/*  948 */       AstConcatenation jjtn001 = new AstConcatenation(18);
/*  949 */       boolean jjtc001 = true;
/*  950 */       this.jjtree.openNodeScope(jjtn001);
/*      */       try {
/*  952 */         Math();
/*      */       } catch (Throwable jjte001) {
/*  954 */         if (jjtc001) {
/*  955 */           this.jjtree.clearNodeScope(jjtn001);
/*  956 */           jjtc001 = false;
/*      */         } else {
/*  958 */           this.jjtree.popNode();
/*      */         }
/*  960 */         if ((jjte001 instanceof RuntimeException)) {
/*  961 */           throw ((RuntimeException)jjte001);
/*      */         }
/*  963 */         if ((jjte001 instanceof ParseException)) {
/*  964 */           throw ((ParseException)jjte001);
/*      */         }
/*  966 */         throw ((Error)jjte001);
/*      */       } finally {
/*  968 */         if (jjtc001) {
/*  969 */           this.jjtree.closeNodeScope(jjtn001, 2);
/*      */         }
/*      */       }
/*      */     }
/*      */   }
/*      */   
/*      */ 
/*      */ 
/*      */   public final void Math()
/*      */     throws ParseException
/*      */   {
/*  980 */     Multiplication();
/*      */     for (;;)
/*      */     {
/*  983 */       switch (this.jj_ntk == -1 ? jj_ntk() : this.jj_ntk)
/*      */       {
/*      */       case 46: 
/*      */       case 47: 
/*      */         break;
/*      */       default: 
/*  989 */         this.jj_la1[25] = this.jj_gen;
/*  990 */         break;
/*      */       }
/*  992 */       switch (this.jj_ntk == -1 ? jj_ntk() : this.jj_ntk) {
/*      */       case 46: 
/*  994 */         jj_consume_token(46);
/*  995 */         AstPlus jjtn001 = new AstPlus(19);
/*  996 */         boolean jjtc001 = true;
/*  997 */         this.jjtree.openNodeScope(jjtn001);
/*      */         try {
/*  999 */           Multiplication();
/*      */         } catch (Throwable jjte001) {
/* 1001 */           if (jjtc001) {
/* 1002 */             this.jjtree.clearNodeScope(jjtn001);
/* 1003 */             jjtc001 = false;
/*      */           } else {
/* 1005 */             this.jjtree.popNode();
/*      */           }
/* 1007 */           if ((jjte001 instanceof RuntimeException)) {
/* 1008 */             throw ((RuntimeException)jjte001);
/*      */           }
/* 1010 */           if ((jjte001 instanceof ParseException)) {
/* 1011 */             throw ((ParseException)jjte001);
/*      */           }
/* 1013 */           throw ((Error)jjte001);
/*      */         } finally {
/* 1015 */           if (jjtc001) {
/* 1016 */             this.jjtree.closeNodeScope(jjtn001, 2);
/*      */           }
/*      */         }
/* 1019 */         break;
/*      */       case 47: 
/* 1021 */         jj_consume_token(47);
/* 1022 */         AstMinus jjtn002 = new AstMinus(20);
/* 1023 */         boolean jjtc002 = true;
/* 1024 */         this.jjtree.openNodeScope(jjtn002);
/*      */         try {
/* 1026 */           Multiplication();
/*      */         } catch (Throwable jjte002) {
/* 1028 */           if (jjtc002) {
/* 1029 */             this.jjtree.clearNodeScope(jjtn002);
/* 1030 */             jjtc002 = false;
/*      */           } else {
/* 1032 */             this.jjtree.popNode();
/*      */           }
/* 1034 */           if ((jjte002 instanceof RuntimeException)) {
/* 1035 */             throw ((RuntimeException)jjte002);
/*      */           }
/* 1037 */           if ((jjte002 instanceof ParseException)) {
/* 1038 */             throw ((ParseException)jjte002);
/*      */           }
/* 1040 */           throw ((Error)jjte002);
/*      */         } finally {
/* 1042 */           if (jjtc002) {
/* 1043 */             this.jjtree.closeNodeScope(jjtn002, 2);
/*      */           }
/*      */         }
/*      */       }
/*      */     }
/* 1048 */     this.jj_la1[26] = this.jj_gen;
/* 1049 */     jj_consume_token(-1);
/* 1050 */     throw new ParseException();
/*      */   }
/*      */   
/*      */ 
/*      */ 
/*      */ 
/*      */ 
/*      */   public final void Multiplication()
/*      */     throws ParseException
/*      */   {
/* 1060 */     Unary();
/*      */     for (;;)
/*      */     {
/* 1063 */       switch (this.jj_ntk == -1 ? jj_ntk() : this.jj_ntk) {
/*      */       case 45: case 49: 
/*      */       case 50: 
/*      */       case 51: 
/*      */       case 52: 
/*      */         break;
/*      */       case 46: case 47: 
/*      */       case 48: 
/*      */       default: 
/* 1072 */         this.jj_la1[27] = this.jj_gen;
/* 1073 */         break;
/*      */       }
/* 1075 */       switch (this.jj_ntk == -1 ? jj_ntk() : this.jj_ntk) {
/*      */       case 45: 
/* 1077 */         jj_consume_token(45);
/* 1078 */         AstMult jjtn001 = new AstMult(21);
/* 1079 */         boolean jjtc001 = true;
/* 1080 */         this.jjtree.openNodeScope(jjtn001);
/*      */         try {
/* 1082 */           Unary();
/*      */         } catch (Throwable jjte001) {
/* 1084 */           if (jjtc001) {
/* 1085 */             this.jjtree.clearNodeScope(jjtn001);
/* 1086 */             jjtc001 = false;
/*      */           } else {
/* 1088 */             this.jjtree.popNode();
/*      */           }
/* 1090 */           if ((jjte001 instanceof RuntimeException)) {
/* 1091 */             throw ((RuntimeException)jjte001);
/*      */           }
/* 1093 */           if ((jjte001 instanceof ParseException)) {
/* 1094 */             throw ((ParseException)jjte001);
/*      */           }
/* 1096 */           throw ((Error)jjte001);
/*      */         } finally {
/* 1098 */           if (jjtc001) {
/* 1099 */             this.jjtree.closeNodeScope(jjtn001, 2);
/*      */           }
/*      */         }
/* 1102 */         break;
/*      */       case 49: 
/*      */       case 50: 
/* 1105 */         switch (this.jj_ntk == -1 ? jj_ntk() : this.jj_ntk) {
/*      */         case 49: 
/* 1107 */           jj_consume_token(49);
/* 1108 */           break;
/*      */         case 50: 
/* 1110 */           jj_consume_token(50);
/* 1111 */           break;
/*      */         default: 
/* 1113 */           this.jj_la1[28] = this.jj_gen;
/* 1114 */           jj_consume_token(-1);
/* 1115 */           throw new ParseException();
/*      */         }
/* 1117 */         AstDiv jjtn002 = new AstDiv(22);
/* 1118 */         boolean jjtc002 = true;
/* 1119 */         this.jjtree.openNodeScope(jjtn002);
/*      */         try {
/* 1121 */           Unary();
/*      */         } catch (Throwable jjte002) {
/* 1123 */           if (jjtc002) {
/* 1124 */             this.jjtree.clearNodeScope(jjtn002);
/* 1125 */             jjtc002 = false;
/*      */           } else {
/* 1127 */             this.jjtree.popNode();
/*      */           }
/* 1129 */           if ((jjte002 instanceof RuntimeException)) {
/* 1130 */             throw ((RuntimeException)jjte002);
/*      */           }
/* 1132 */           if ((jjte002 instanceof ParseException)) {
/* 1133 */             throw ((ParseException)jjte002);
/*      */           }
/* 1135 */           throw ((Error)jjte002);
/*      */         } finally {
/* 1137 */           if (jjtc002) {
/* 1138 */             this.jjtree.closeNodeScope(jjtn002, 2);
/*      */           }
/*      */         }
/* 1141 */         break;
/*      */       case 51: 
/*      */       case 52: 
/* 1144 */         switch (this.jj_ntk == -1 ? jj_ntk() : this.jj_ntk) {
/*      */         case 51: 
/* 1146 */           jj_consume_token(51);
/* 1147 */           break;
/*      */         case 52: 
/* 1149 */           jj_consume_token(52);
/* 1150 */           break;
/*      */         default: 
/* 1152 */           this.jj_la1[29] = this.jj_gen;
/* 1153 */           jj_consume_token(-1);
/* 1154 */           throw new ParseException();
/*      */         }
/* 1156 */         AstMod jjtn003 = new AstMod(23);
/* 1157 */         boolean jjtc003 = true;
/* 1158 */         this.jjtree.openNodeScope(jjtn003);
/*      */         try {
/* 1160 */           Unary();
/*      */         } catch (Throwable jjte003) {
/* 1162 */           if (jjtc003) {
/* 1163 */             this.jjtree.clearNodeScope(jjtn003);
/* 1164 */             jjtc003 = false;
/*      */           } else {
/* 1166 */             this.jjtree.popNode();
/*      */           }
/* 1168 */           if ((jjte003 instanceof RuntimeException)) {
/* 1169 */             throw ((RuntimeException)jjte003);
/*      */           }
/* 1171 */           if ((jjte003 instanceof ParseException)) {
/* 1172 */             throw ((ParseException)jjte003);
/*      */           }
/* 1174 */           throw ((Error)jjte003);
/*      */         } finally {
/* 1176 */           if (jjtc003) {
/* 1177 */             this.jjtree.closeNodeScope(jjtn003, 2);
/*      */           }
/*      */         }
/*      */       }
/*      */     }
/* 1182 */     this.jj_la1[30] = this.jj_gen;
/* 1183 */     jj_consume_token(-1);
/* 1184 */     throw new ParseException();
/*      */   }
/*      */   
/*      */ 
/*      */ 
/*      */ 
/*      */ 
/*      */   public final void Unary()
/*      */     throws ParseException
/*      */   {
/* 1194 */     switch (this.jj_ntk == -1 ? jj_ntk() : this.jj_ntk) {
/*      */     case 47: 
/* 1196 */       jj_consume_token(47);
/* 1197 */       AstNegative jjtn001 = new AstNegative(24);
/* 1198 */       boolean jjtc001 = true;
/* 1199 */       this.jjtree.openNodeScope(jjtn001);
/*      */       try {
/* 1201 */         Unary();
/*      */       } catch (Throwable jjte001) {
/* 1203 */         if (jjtc001) {
/* 1204 */           this.jjtree.clearNodeScope(jjtn001);
/* 1205 */           jjtc001 = false;
/*      */         } else {
/* 1207 */           this.jjtree.popNode();
/*      */         }
/* 1209 */         if ((jjte001 instanceof RuntimeException)) {
/* 1210 */           throw ((RuntimeException)jjte001);
/*      */         }
/* 1212 */         if ((jjte001 instanceof ParseException)) {
/* 1213 */           throw ((ParseException)jjte001);
/*      */         }
/* 1215 */         throw ((Error)jjte001);
/*      */       } finally {
/* 1217 */         if (jjtc001) {
/* 1218 */           this.jjtree.closeNodeScope(jjtn001, true);
/*      */         }
/*      */       }
/* 1221 */       break;
/*      */     case 37: 
/*      */     case 38: 
/* 1224 */       switch (this.jj_ntk == -1 ? jj_ntk() : this.jj_ntk) {
/*      */       case 37: 
/* 1226 */         jj_consume_token(37);
/* 1227 */         break;
/*      */       case 38: 
/* 1229 */         jj_consume_token(38);
/* 1230 */         break;
/*      */       default: 
/* 1232 */         this.jj_la1[31] = this.jj_gen;
/* 1233 */         jj_consume_token(-1);
/* 1234 */         throw new ParseException();
/*      */       }
/* 1236 */       AstNot jjtn002 = new AstNot(25);
/* 1237 */       boolean jjtc002 = true;
/* 1238 */       this.jjtree.openNodeScope(jjtn002);
/*      */       try {
/* 1240 */         Unary();
/*      */       } catch (Throwable jjte002) {
/* 1242 */         if (jjtc002) {
/* 1243 */           this.jjtree.clearNodeScope(jjtn002);
/* 1244 */           jjtc002 = false;
/*      */         } else {
/* 1246 */           this.jjtree.popNode();
/*      */         }
/* 1248 */         if ((jjte002 instanceof RuntimeException)) {
/* 1249 */           throw ((RuntimeException)jjte002);
/*      */         }
/* 1251 */         if ((jjte002 instanceof ParseException)) {
/* 1252 */           throw ((ParseException)jjte002);
/*      */         }
/* 1254 */         throw ((Error)jjte002);
/*      */       } finally {
/* 1256 */         if (jjtc002) {
/* 1257 */           this.jjtree.closeNodeScope(jjtn002, true);
/*      */         }
/*      */       }
/* 1260 */       break;
/*      */     case 43: 
/* 1262 */       jj_consume_token(43);
/* 1263 */       AstEmpty jjtn003 = new AstEmpty(26);
/* 1264 */       boolean jjtc003 = true;
/* 1265 */       this.jjtree.openNodeScope(jjtn003);
/*      */       try {
/* 1267 */         Unary();
/*      */       } catch (Throwable jjte003) {
/* 1269 */         if (jjtc003) {
/* 1270 */           this.jjtree.clearNodeScope(jjtn003);
/* 1271 */           jjtc003 = false;
/*      */         } else {
/* 1273 */           this.jjtree.popNode();
/*      */         }
/* 1275 */         if ((jjte003 instanceof RuntimeException)) {
/* 1276 */           throw ((RuntimeException)jjte003);
/*      */         }
/* 1278 */         if ((jjte003 instanceof ParseException)) {
/* 1279 */           throw ((ParseException)jjte003);
/*      */         }
/* 1281 */         throw ((Error)jjte003);
/*      */       } finally {
/* 1283 */         if (jjtc003) {
/* 1284 */           this.jjtree.closeNodeScope(jjtn003, true);
/*      */         }
/*      */       }
/* 1287 */       break;
/*      */     case 8: 
/*      */     case 10: 
/*      */     case 11: 
/*      */     case 13: 
/*      */     case 14: 
/*      */     case 15: 
/*      */     case 16: 
/*      */     case 18: 
/*      */     case 20: 
/*      */     case 56: 
/* 1298 */       Value();
/* 1299 */       break;
/*      */     case 9: case 12: case 17: case 19: case 21: case 22: case 23: case 24: case 25: case 26: case 27: case 28: case 29: case 30: case 31: case 32: case 33: case 34: case 35: case 36: case 39: case 40: case 41: case 42: case 44: case 45: case 46: case 48: case 49: case 50: case 51: case 52: case 53: case 54: case 55: default: 
/* 1301 */       this.jj_la1[32] = this.jj_gen;
/* 1302 */       jj_consume_token(-1);
/* 1303 */       throw new ParseException();
/*      */     }
/*      */     
/*      */   }
/*      */   
/*      */ 
/*      */   public final void Value()
/*      */     throws ParseException
/*      */   {
/* 1312 */     AstValue jjtn001 = new AstValue(27);
/* 1313 */     boolean jjtc001 = true;
/* 1314 */     this.jjtree.openNodeScope(jjtn001);
/*      */     try {
/* 1316 */       ValuePrefix();
/*      */       for (;;)
/*      */       {
/* 1319 */         switch (this.jj_ntk == -1 ? jj_ntk() : this.jj_ntk)
/*      */         {
/*      */         case 17: 
/*      */         case 20: 
/*      */           break;
/*      */         default: 
/* 1325 */           this.jj_la1[33] = this.jj_gen;
/* 1326 */           break;
/*      */         }
/* 1328 */         ValueSuffix();
/*      */       }
/*      */     } catch (Throwable jjte001) {
/* 1331 */       if (jjtc001) {
/* 1332 */         this.jjtree.clearNodeScope(jjtn001);
/* 1333 */         jjtc001 = false;
/*      */       } else {
/* 1335 */         this.jjtree.popNode();
/*      */       }
/* 1337 */       if ((jjte001 instanceof RuntimeException)) {
/* 1338 */         throw ((RuntimeException)jjte001);
/*      */       }
/* 1340 */       if ((jjte001 instanceof ParseException)) {
/* 1341 */         throw ((ParseException)jjte001);
/*      */       }
/* 1343 */       throw ((Error)jjte001);
/*      */     } finally {
/* 1345 */       if (jjtc001) {
/* 1346 */         this.jjtree.closeNodeScope(jjtn001, this.jjtree.nodeArity() > 1);
/*      */       }
/*      */     }
/*      */   }
/*      */   
/*      */ 
/*      */ 
/*      */   public final void ValuePrefix()
/*      */     throws ParseException
/*      */   {
/* 1356 */     switch (this.jj_ntk == -1 ? jj_ntk() : this.jj_ntk) {
/*      */     case 10: 
/*      */     case 11: 
/*      */     case 13: 
/*      */     case 14: 
/*      */     case 15: 
/*      */     case 16: 
/* 1363 */       Literal();
/* 1364 */       break;
/*      */     case 8: 
/*      */     case 18: 
/*      */     case 20: 
/*      */     case 56: 
/* 1369 */       NonLiteral();
/* 1370 */       break;
/*      */     default: 
/* 1372 */       this.jj_la1[34] = this.jj_gen;
/* 1373 */       jj_consume_token(-1);
/* 1374 */       throw new ParseException();
/*      */     }
/*      */     
/*      */   }
/*      */   
/*      */ 
/*      */   public final void ValueSuffix()
/*      */     throws ParseException
/*      */   {
/* 1383 */     switch (this.jj_ntk == -1 ? jj_ntk() : this.jj_ntk) {
/*      */     case 17: 
/* 1385 */       DotSuffix();
/* 1386 */       break;
/*      */     case 20: 
/* 1388 */       BracketSuffix();
/* 1389 */       break;
/*      */     default: 
/* 1391 */       this.jj_la1[35] = this.jj_gen;
/* 1392 */       jj_consume_token(-1);
/* 1393 */       throw new ParseException();
/*      */     }
/* 1395 */     switch (this.jj_ntk == -1 ? jj_ntk() : this.jj_ntk) {
/*      */     case 18: 
/* 1397 */       MethodParameters();
/* 1398 */       break;
/*      */     default: 
/* 1400 */       this.jj_la1[36] = this.jj_gen;
/*      */     }
/*      */     
/*      */   }
/*      */   
/*      */ 
/*      */ 
/*      */ 
/*      */   public final void DotSuffix()
/*      */     throws ParseException
/*      */   {
/* 1411 */     AstDotSuffix jjtn000 = new AstDotSuffix(28);
/* 1412 */     boolean jjtc000 = true;
/* 1413 */     this.jjtree.openNodeScope(jjtn000);Token t = null;
/*      */     try {
/* 1415 */       jj_consume_token(17);
/* 1416 */       t = jj_consume_token(56);
/* 1417 */       this.jjtree.closeNodeScope(jjtn000, true);
/* 1418 */       jjtc000 = false;
/* 1419 */       jjtn000.setImage(t.image);
/*      */     } finally {
/* 1421 */       if (jjtc000) {
/* 1422 */         this.jjtree.closeNodeScope(jjtn000, true);
/*      */       }
/*      */     }
/*      */   }
/*      */   
/*      */ 
/*      */ 
/*      */ 
/*      */   public final void BracketSuffix()
/*      */     throws ParseException
/*      */   {
/* 1433 */     AstBracketSuffix jjtn000 = new AstBracketSuffix(29);
/* 1434 */     boolean jjtc000 = true;
/* 1435 */     this.jjtree.openNodeScope(jjtn000);
/*      */     try {
/* 1437 */       jj_consume_token(20);
/* 1438 */       Expression();
/* 1439 */       jj_consume_token(21);
/*      */     } catch (Throwable jjte000) {
/* 1441 */       if (jjtc000) {
/* 1442 */         this.jjtree.clearNodeScope(jjtn000);
/* 1443 */         jjtc000 = false;
/*      */       } else {
/* 1445 */         this.jjtree.popNode();
/*      */       }
/* 1447 */       if ((jjte000 instanceof RuntimeException)) {
/* 1448 */         throw ((RuntimeException)jjte000);
/*      */       }
/* 1450 */       if ((jjte000 instanceof ParseException)) {
/* 1451 */         throw ((ParseException)jjte000);
/*      */       }
/* 1453 */       throw ((Error)jjte000);
/*      */     } finally {
/* 1455 */       if (jjtc000) {
/* 1456 */         this.jjtree.closeNodeScope(jjtn000, true);
/*      */       }
/*      */     }
/*      */   }
/*      */   
/*      */ 
/*      */ 
/*      */   public final void MethodParameters()
/*      */     throws ParseException
/*      */   {
/* 1466 */     AstMethodParameters jjtn000 = new AstMethodParameters(30);
/* 1467 */     boolean jjtc000 = true;
/* 1468 */     this.jjtree.openNodeScope(jjtn000);
/*      */     try {
/* 1470 */       jj_consume_token(18);
/* 1471 */       switch (this.jj_ntk == -1 ? jj_ntk() : this.jj_ntk) {
/*      */       case 8: 
/*      */       case 10: 
/*      */       case 11: 
/*      */       case 13: 
/*      */       case 14: 
/*      */       case 15: 
/*      */       case 16: 
/*      */       case 18: 
/*      */       case 20: 
/*      */       case 37: 
/*      */       case 38: 
/*      */       case 43: 
/*      */       case 47: 
/*      */       case 56: 
/* 1486 */         Expression();
/*      */         for (;;)
/*      */         {
/* 1489 */           switch (this.jj_ntk == -1 ? jj_ntk() : this.jj_ntk)
/*      */           {
/*      */           case 24: 
/*      */             break;
/*      */           default: 
/* 1494 */             this.jj_la1[37] = this.jj_gen;
/* 1495 */             break;
/*      */           }
/* 1497 */           jj_consume_token(24);
/* 1498 */           Expression();
/*      */         }
/*      */       }
/*      */       
/* 1502 */       this.jj_la1[38] = this.jj_gen;
/*      */       
/*      */ 
/* 1505 */       jj_consume_token(19);
/*      */     } catch (Throwable jjte000) {
/* 1507 */       if (jjtc000) {
/* 1508 */         this.jjtree.clearNodeScope(jjtn000);
/* 1509 */         jjtc000 = false;
/*      */       } else {
/* 1511 */         this.jjtree.popNode();
/*      */       }
/* 1513 */       if ((jjte000 instanceof RuntimeException)) {
/* 1514 */         throw ((RuntimeException)jjte000);
/*      */       }
/* 1516 */       if ((jjte000 instanceof ParseException)) {
/* 1517 */         throw ((ParseException)jjte000);
/*      */       }
/* 1519 */       throw ((Error)jjte000);
/*      */     } finally {
/* 1521 */       if (jjtc000) {
/* 1522 */         this.jjtree.closeNodeScope(jjtn000, true);
/*      */       }
/*      */     }
/*      */   }
/*      */   
/*      */ 
/*      */ 
/*      */   public final void NonLiteral()
/*      */     throws ParseException
/*      */   {
/* 1532 */     if (jj_2_6(5)) {
/* 1533 */       LambdaExpressionOrInvocation();
/*      */     } else {
/* 1535 */       switch (this.jj_ntk == -1 ? jj_ntk() : this.jj_ntk) {
/*      */       case 18: 
/* 1537 */         jj_consume_token(18);
/* 1538 */         Expression();
/* 1539 */         jj_consume_token(19);
/* 1540 */         break;
/*      */       default: 
/* 1542 */         this.jj_la1[39] = this.jj_gen;
/* 1543 */         if (jj_2_7(Integer.MAX_VALUE)) {
/* 1544 */           Function();
/*      */         } else {
/* 1546 */           switch (this.jj_ntk == -1 ? jj_ntk() : this.jj_ntk) {
/*      */           case 56: 
/* 1548 */             Identifier();
/* 1549 */             break;
/*      */           default: 
/* 1551 */             this.jj_la1[40] = this.jj_gen;
/* 1552 */             if (jj_2_8(3)) {
/* 1553 */               SetData();
/*      */             } else {
/* 1555 */               switch (this.jj_ntk == -1 ? jj_ntk() : this.jj_ntk) {
/*      */               case 20: 
/* 1557 */                 ListData();
/* 1558 */                 break;
/*      */               case 8: 
/* 1560 */                 MapData();
/* 1561 */                 break;
/*      */               default: 
/* 1563 */                 this.jj_la1[41] = this.jj_gen;
/* 1564 */                 jj_consume_token(-1);
/* 1565 */                 throw new ParseException();
/*      */               }
/*      */               
/*      */             }
/*      */             break;
/*      */           }
/*      */           
/*      */         }
/*      */         break;
/*      */       }
/*      */     }
/*      */   }
/*      */   
/*      */   public final void SetData()
/*      */     throws ParseException
/*      */   {
/* 1581 */     AstSetData jjtn000 = new AstSetData(31);
/* 1582 */     boolean jjtc000 = true;
/* 1583 */     this.jjtree.openNodeScope(jjtn000);
/*      */     try {
/* 1585 */       jj_consume_token(8);
/* 1586 */       switch (this.jj_ntk == -1 ? jj_ntk() : this.jj_ntk) {
/*      */       case 8: 
/*      */       case 10: 
/*      */       case 11: 
/*      */       case 13: 
/*      */       case 14: 
/*      */       case 15: 
/*      */       case 16: 
/*      */       case 18: 
/*      */       case 20: 
/*      */       case 37: 
/*      */       case 38: 
/*      */       case 43: 
/*      */       case 47: 
/*      */       case 56: 
/* 1601 */         Expression();
/*      */         for (;;)
/*      */         {
/* 1604 */           switch (this.jj_ntk == -1 ? jj_ntk() : this.jj_ntk)
/*      */           {
/*      */           case 24: 
/*      */             break;
/*      */           default: 
/* 1609 */             this.jj_la1[42] = this.jj_gen;
/* 1610 */             break;
/*      */           }
/* 1612 */           jj_consume_token(24);
/* 1613 */           Expression();
/*      */         }
/*      */       }
/*      */       
/* 1617 */       this.jj_la1[43] = this.jj_gen;
/*      */       
/*      */ 
/* 1620 */       jj_consume_token(9);
/*      */     } catch (Throwable jjte000) {
/* 1622 */       if (jjtc000) {
/* 1623 */         this.jjtree.clearNodeScope(jjtn000);
/* 1624 */         jjtc000 = false;
/*      */       } else {
/* 1626 */         this.jjtree.popNode();
/*      */       }
/* 1628 */       if ((jjte000 instanceof RuntimeException)) {
/* 1629 */         throw ((RuntimeException)jjte000);
/*      */       }
/* 1631 */       if ((jjte000 instanceof ParseException)) {
/* 1632 */         throw ((ParseException)jjte000);
/*      */       }
/* 1634 */       throw ((Error)jjte000);
/*      */     } finally {
/* 1636 */       if (jjtc000) {
/* 1637 */         this.jjtree.closeNodeScope(jjtn000, true);
/*      */       }
/*      */     }
/*      */   }
/*      */   
/*      */   public final void ListData() throws ParseException
/*      */   {
/* 1644 */     AstListData jjtn000 = new AstListData(32);
/* 1645 */     boolean jjtc000 = true;
/* 1646 */     this.jjtree.openNodeScope(jjtn000);
/*      */     try {
/* 1648 */       jj_consume_token(20);
/* 1649 */       switch (this.jj_ntk == -1 ? jj_ntk() : this.jj_ntk) {
/*      */       case 8: 
/*      */       case 10: 
/*      */       case 11: 
/*      */       case 13: 
/*      */       case 14: 
/*      */       case 15: 
/*      */       case 16: 
/*      */       case 18: 
/*      */       case 20: 
/*      */       case 37: 
/*      */       case 38: 
/*      */       case 43: 
/*      */       case 47: 
/*      */       case 56: 
/* 1664 */         Expression();
/*      */         for (;;)
/*      */         {
/* 1667 */           switch (this.jj_ntk == -1 ? jj_ntk() : this.jj_ntk)
/*      */           {
/*      */           case 24: 
/*      */             break;
/*      */           default: 
/* 1672 */             this.jj_la1[44] = this.jj_gen;
/* 1673 */             break;
/*      */           }
/* 1675 */           jj_consume_token(24);
/* 1676 */           Expression();
/*      */         }
/*      */       }
/*      */       
/* 1680 */       this.jj_la1[45] = this.jj_gen;
/*      */       
/*      */ 
/* 1683 */       jj_consume_token(21);
/*      */     } catch (Throwable jjte000) {
/* 1685 */       if (jjtc000) {
/* 1686 */         this.jjtree.clearNodeScope(jjtn000);
/* 1687 */         jjtc000 = false;
/*      */       } else {
/* 1689 */         this.jjtree.popNode();
/*      */       }
/* 1691 */       if ((jjte000 instanceof RuntimeException)) {
/* 1692 */         throw ((RuntimeException)jjte000);
/*      */       }
/* 1694 */       if ((jjte000 instanceof ParseException)) {
/* 1695 */         throw ((ParseException)jjte000);
/*      */       }
/* 1697 */       throw ((Error)jjte000);
/*      */     } finally {
/* 1699 */       if (jjtc000) {
/* 1700 */         this.jjtree.closeNodeScope(jjtn000, true);
/*      */       }
/*      */     }
/*      */   }
/*      */   
/*      */ 
/*      */ 
/*      */ 
/*      */ 
/*      */   public final void MapData()
/*      */     throws ParseException
/*      */   {
/* 1712 */     AstMapData jjtn000 = new AstMapData(33);
/* 1713 */     boolean jjtc000 = true;
/* 1714 */     this.jjtree.openNodeScope(jjtn000);
/*      */     try {
/* 1716 */       jj_consume_token(8);
/* 1717 */       switch (this.jj_ntk == -1 ? jj_ntk() : this.jj_ntk) {
/*      */       case 8: 
/*      */       case 10: 
/*      */       case 11: 
/*      */       case 13: 
/*      */       case 14: 
/*      */       case 15: 
/*      */       case 16: 
/*      */       case 18: 
/*      */       case 20: 
/*      */       case 37: 
/*      */       case 38: 
/*      */       case 43: 
/*      */       case 47: 
/*      */       case 56: 
/* 1732 */         MapEntry();
/*      */         for (;;)
/*      */         {
/* 1735 */           switch (this.jj_ntk == -1 ? jj_ntk() : this.jj_ntk)
/*      */           {
/*      */           case 24: 
/*      */             break;
/*      */           default: 
/* 1740 */             this.jj_la1[46] = this.jj_gen;
/* 1741 */             break;
/*      */           }
/* 1743 */           jj_consume_token(24);
/* 1744 */           MapEntry();
/*      */         }
/*      */       }
/*      */       
/* 1748 */       this.jj_la1[47] = this.jj_gen;
/*      */       
/*      */ 
/* 1751 */       jj_consume_token(9);
/*      */     } catch (Throwable jjte000) {
/* 1753 */       if (jjtc000) {
/* 1754 */         this.jjtree.clearNodeScope(jjtn000);
/* 1755 */         jjtc000 = false;
/*      */       } else {
/* 1757 */         this.jjtree.popNode();
/*      */       }
/* 1759 */       if ((jjte000 instanceof RuntimeException)) {
/* 1760 */         throw ((RuntimeException)jjte000);
/*      */       }
/* 1762 */       if ((jjte000 instanceof ParseException)) {
/* 1763 */         throw ((ParseException)jjte000);
/*      */       }
/* 1765 */       throw ((Error)jjte000);
/*      */     } finally {
/* 1767 */       if (jjtc000) {
/* 1768 */         this.jjtree.closeNodeScope(jjtn000, true);
/*      */       }
/*      */     }
/*      */   }
/*      */   
/*      */   public final void MapEntry() throws ParseException
/*      */   {
/* 1775 */     AstMapEntry jjtn000 = new AstMapEntry(34);
/* 1776 */     boolean jjtc000 = true;
/* 1777 */     this.jjtree.openNodeScope(jjtn000);
/*      */     try {
/* 1779 */       Expression();
/* 1780 */       jj_consume_token(22);
/* 1781 */       Expression();
/*      */     } catch (Throwable jjte000) {
/* 1783 */       if (jjtc000) {
/* 1784 */         this.jjtree.clearNodeScope(jjtn000);
/* 1785 */         jjtc000 = false;
/*      */       } else {
/* 1787 */         this.jjtree.popNode();
/*      */       }
/* 1789 */       if ((jjte000 instanceof RuntimeException)) {
/* 1790 */         throw ((RuntimeException)jjte000);
/*      */       }
/* 1792 */       if ((jjte000 instanceof ParseException)) {
/* 1793 */         throw ((ParseException)jjte000);
/*      */       }
/* 1795 */       throw ((Error)jjte000);
/*      */     } finally {
/* 1797 */       if (jjtc000) {
/* 1798 */         this.jjtree.closeNodeScope(jjtn000, true);
/*      */       }
/*      */     }
/*      */   }
/*      */   
/*      */ 
/*      */ 
/*      */ 
/*      */   public final void Identifier()
/*      */     throws ParseException
/*      */   {
/* 1809 */     AstIdentifier jjtn000 = new AstIdentifier(35);
/* 1810 */     boolean jjtc000 = true;
/* 1811 */     this.jjtree.openNodeScope(jjtn000);Token t = null;
/*      */     try {
/* 1813 */       t = jj_consume_token(56);
/* 1814 */       this.jjtree.closeNodeScope(jjtn000, true);
/* 1815 */       jjtc000 = false;
/* 1816 */       jjtn000.setImage(t.image);
/*      */     } finally {
/* 1818 */       if (jjtc000) {
/* 1819 */         this.jjtree.closeNodeScope(jjtn000, true);
/*      */       }
/*      */     }
/*      */   }
/*      */   
/*      */ 
/*      */ 
/*      */ 
/*      */   public final void Function()
/*      */     throws ParseException
/*      */   {
/* 1830 */     AstFunction jjtn000 = new AstFunction(36);
/* 1831 */     boolean jjtc000 = true;
/* 1832 */     this.jjtree.openNodeScope(jjtn000);Token t0 = null;
/* 1833 */     Token t1 = null;
/*      */     try {
/* 1835 */       t0 = jj_consume_token(56);
/* 1836 */       switch (this.jj_ntk == -1 ? jj_ntk() : this.jj_ntk) {
/*      */       case 22: 
/* 1838 */         jj_consume_token(22);
/* 1839 */         t1 = jj_consume_token(56);
/* 1840 */         break;
/*      */       default: 
/* 1842 */         this.jj_la1[48] = this.jj_gen;
/*      */       }
/*      */       
/* 1845 */       if (t1 != null) {
/* 1846 */         jjtn000.setPrefix(t0.image);
/* 1847 */         jjtn000.setLocalName(t1.image);
/*      */       } else {
/* 1849 */         jjtn000.setLocalName(t0.image);
/*      */       }
/*      */       for (;;)
/*      */       {
/* 1853 */         MethodParameters();
/* 1854 */         switch (this.jj_ntk == -1 ? jj_ntk() : this.jj_ntk)
/*      */         {
/*      */         }
/*      */         
/*      */       }
/* 1859 */       this.jj_la1[49] = this.jj_gen;
/*      */ 
/*      */     }
/*      */     catch (Throwable jjte000)
/*      */     {
/* 1864 */       if (jjtc000) {
/* 1865 */         this.jjtree.clearNodeScope(jjtn000);
/* 1866 */         jjtc000 = false;
/*      */       } else {
/* 1868 */         this.jjtree.popNode();
/*      */       }
/* 1870 */       if ((jjte000 instanceof RuntimeException)) {
/* 1871 */         throw ((RuntimeException)jjte000);
/*      */       }
/* 1873 */       if ((jjte000 instanceof ParseException)) {
/* 1874 */         throw ((ParseException)jjte000);
/*      */       }
/* 1876 */       throw ((Error)jjte000);
/*      */     } finally {
/* 1878 */       if (jjtc000) {
/* 1879 */         this.jjtree.closeNodeScope(jjtn000, true);
/*      */       }
/*      */     }
/*      */   }
/*      */   
/*      */ 
/*      */ 
/*      */   public final void Literal()
/*      */     throws ParseException
/*      */   {
/* 1889 */     switch (this.jj_ntk == -1 ? jj_ntk() : this.jj_ntk) {
/*      */     case 14: 
/*      */     case 15: 
/* 1892 */       Boolean();
/* 1893 */       break;
/*      */     case 11: 
/* 1895 */       FloatingPoint();
/* 1896 */       break;
/*      */     case 10: 
/* 1898 */       Integer();
/* 1899 */       break;
/*      */     case 13: 
/* 1901 */       String();
/* 1902 */       break;
/*      */     case 16: 
/* 1904 */       Null();
/* 1905 */       break;
/*      */     case 12: default: 
/* 1907 */       this.jj_la1[50] = this.jj_gen;
/* 1908 */       jj_consume_token(-1);
/* 1909 */       throw new ParseException();
/*      */     }
/*      */     
/*      */   }
/*      */   
/*      */ 
/*      */ 
/*      */ 
/*      */ 
/*      */   SimpleCharStream jj_input_stream;
/*      */   
/*      */ 
/*      */ 
/*      */ 
/*      */   public Token token;
/*      */   
/*      */ 
/*      */ 
/*      */ 
/*      */   public Token jj_nt;
/*      */   
/*      */ 
/*      */ 
/*      */ 
/*      */   private int jj_ntk;
/*      */   
/*      */ 
/*      */ 
/*      */   private Token jj_scanpos;
/*      */   
/*      */ 
/*      */ 
/*      */   private Token jj_lastpos;
/*      */   
/*      */ 
/*      */ 
/*      */   private int jj_la;
/*      */   
/*      */ 
/*      */ 
/*      */   private int jj_gen;
/*      */   
/*      */ 
/*      */ 
/*      */   public final void FloatingPoint()
/*      */     throws ParseException
/*      */   {
/* 1956 */     AstFloatingPoint jjtn000 = new AstFloatingPoint(39);
/* 1957 */     boolean jjtc000 = true;
/* 1958 */     this.jjtree.openNodeScope(jjtn000);Token t = null;
/*      */     try {
/* 1960 */       t = jj_consume_token(11);
/* 1961 */       this.jjtree.closeNodeScope(jjtn000, true);
/* 1962 */       jjtc000 = false;
/* 1963 */       jjtn000.setImage(t.image);
/*      */     } finally {
/* 1965 */       if (jjtc000) {
/* 1966 */         this.jjtree.closeNodeScope(jjtn000, true);
/*      */       }
/*      */     }
/*      */   }
/*      */   
/*      */ 
/*      */ 
/*      */ 
/*      */   public final void Integer()
/*      */     throws ParseException
/*      */   {
/* 1977 */     AstInteger jjtn000 = new AstInteger(40);
/* 1978 */     boolean jjtc000 = true;
/* 1979 */     this.jjtree.openNodeScope(jjtn000);Token t = null;
/*      */     try {
/* 1981 */       t = jj_consume_token(10);
/* 1982 */       this.jjtree.closeNodeScope(jjtn000, true);
/* 1983 */       jjtc000 = false;
/* 1984 */       jjtn000.setImage(t.image);
/*      */     } finally {
/* 1986 */       if (jjtc000) {
/* 1987 */         this.jjtree.closeNodeScope(jjtn000, true);
/*      */       }
/*      */     }
/*      */   }
/*      */   
/*      */ 
/*      */ 
/*      */ 
/*      */   public final void String()
/*      */     throws ParseException
/*      */   {
/* 1998 */     AstString jjtn000 = new AstString(41);
/* 1999 */     boolean jjtc000 = true;
/* 2000 */     this.jjtree.openNodeScope(jjtn000);Token t = null;
/*      */     try {
/* 2002 */       t = jj_consume_token(13);
/* 2003 */       this.jjtree.closeNodeScope(jjtn000, true);
/* 2004 */       jjtc000 = false;
/* 2005 */       jjtn000.setImage(t.image);
/*      */     } finally {
/* 2007 */       if (jjtc000) {
/* 2008 */         this.jjtree.closeNodeScope(jjtn000, true);
/*      */       }
/*      */     }
/*      */   }
/*      */   
/*      */ 
/*      */ 
/*      */ 
/*      */ 
/*      */ 
/*      */ 
/*      */ 
/*      */ 
/*      */ 
/*      */ 
/*      */ 
/*      */ 
/*      */ 
/*      */ 
/*      */ 
/*      */ 
/*      */ 
/*      */   private boolean jj_2_1(int xla)
/*      */   {
/* 2032 */     this.jj_la = xla;this.jj_lastpos = (this.jj_scanpos = this.token);
/* 2033 */     try { return !jj_3_1();
/* 2034 */     } catch (LookaheadSuccess ls) { return true;
/* 2035 */     } finally { jj_save(0, xla);
/*      */     }
/*      */   }
/*      */   
/* 2039 */   private boolean jj_2_2(int xla) { this.jj_la = xla;this.jj_lastpos = (this.jj_scanpos = this.token);
/* 2040 */     try { return !jj_3_2();
/* 2041 */     } catch (LookaheadSuccess ls) { return true;
/* 2042 */     } finally { jj_save(1, xla);
/*      */     }
/*      */   }
/*      */   
/* 2046 */   private boolean jj_2_3(int xla) { this.jj_la = xla;this.jj_lastpos = (this.jj_scanpos = this.token);
/* 2047 */     try { return !jj_3_3();
/* 2048 */     } catch (LookaheadSuccess ls) { return true;
/* 2049 */     } finally { jj_save(2, xla);
/*      */     }
/*      */   }
/*      */   
/* 2053 */   private boolean jj_2_4(int xla) { this.jj_la = xla;this.jj_lastpos = (this.jj_scanpos = this.token);
/* 2054 */     try { return !jj_3_4();
/* 2055 */     } catch (LookaheadSuccess ls) { return true;
/* 2056 */     } finally { jj_save(3, xla);
/*      */     }
/*      */   }
/*      */   
/* 2060 */   private boolean jj_2_5(int xla) { this.jj_la = xla;this.jj_lastpos = (this.jj_scanpos = this.token);
/* 2061 */     try { return !jj_3_5();
/* 2062 */     } catch (LookaheadSuccess ls) { return true;
/* 2063 */     } finally { jj_save(4, xla);
/*      */     }
/*      */   }
/*      */   
/* 2067 */   private boolean jj_2_6(int xla) { this.jj_la = xla;this.jj_lastpos = (this.jj_scanpos = this.token);
/* 2068 */     try { return !jj_3_6();
/* 2069 */     } catch (LookaheadSuccess ls) { return true;
/* 2070 */     } finally { jj_save(5, xla);
/*      */     }
/*      */   }
/*      */   
/* 2074 */   private boolean jj_2_7(int xla) { this.jj_la = xla;this.jj_lastpos = (this.jj_scanpos = this.token);
/* 2075 */     try { return !jj_3_7();
/* 2076 */     } catch (LookaheadSuccess ls) { return true;
/* 2077 */     } finally { jj_save(6, xla);
/*      */     }
/*      */   }
/*      */   
/* 2081 */   private boolean jj_2_8(int xla) { this.jj_la = xla;this.jj_lastpos = (this.jj_scanpos = this.token);
/* 2082 */     try { return !jj_3_8();
/* 2083 */     } catch (LookaheadSuccess ls) { return true;
/* 2084 */     } finally { jj_save(7, xla);
/*      */     }
/*      */   }
/*      */   
/*      */   private boolean jj_3R_41() {
/* 2089 */     Token xsp = this.jj_scanpos;
/* 2090 */     if (jj_scan_token(39)) {
/* 2091 */       this.jj_scanpos = xsp;
/* 2092 */       if (jj_scan_token(40)) return true;
/*      */     }
/* 2094 */     return false;
/*      */   }
/*      */   
/*      */   private boolean jj_3R_30() {
/* 2098 */     if (jj_3R_22()) return true;
/* 2099 */     return false;
/*      */   }
/*      */   
/*      */   private boolean jj_3R_40() {
/* 2103 */     if (jj_3R_44()) return true;
/*      */     Token xsp;
/*      */     do {
/* 2106 */       xsp = this.jj_scanpos;
/* 2107 */     } while (!jj_3R_45()); this.jj_scanpos = xsp;
/*      */     
/* 2109 */     return false;
/*      */   }
/*      */   
/*      */   private boolean jj_3R_107() {
/* 2113 */     if (jj_3R_36()) return true;
/* 2114 */     return false;
/*      */   }
/*      */   
/*      */   private boolean jj_3R_105() {
/* 2118 */     if (jj_3R_107()) return true;
/* 2119 */     return false;
/*      */   }
/*      */   
/*      */   private boolean jj_3R_43() {
/* 2123 */     if (jj_scan_token(24)) return true;
/* 2124 */     if (jj_3R_38()) return true;
/* 2125 */     return false;
/*      */   }
/*      */   
/*      */   private boolean jj_3R_34() {
/* 2129 */     if (jj_3R_40()) return true;
/*      */     Token xsp;
/*      */     do {
/* 2132 */       xsp = this.jj_scanpos;
/* 2133 */     } while (!jj_3R_41()); this.jj_scanpos = xsp;
/*      */     
/* 2135 */     return false;
/*      */   }
/*      */   
/*      */   private boolean jj_3R_37() {
/* 2139 */     if (jj_scan_token(24)) return true;
/* 2140 */     return false;
/*      */   }
/*      */   
/*      */   private boolean jj_3R_35()
/*      */   {
/* 2145 */     Token xsp = this.jj_scanpos;
/* 2146 */     if (jj_scan_token(41)) {
/* 2147 */       this.jj_scanpos = xsp;
/* 2148 */       if (jj_scan_token(42)) return true;
/*      */     }
/* 2150 */     return false;
/*      */   }
/*      */   
/*      */   private boolean jj_3R_99() {
/* 2154 */     if (jj_scan_token(8)) { return true;
/*      */     }
/* 2156 */     Token xsp = this.jj_scanpos;
/* 2157 */     if (jj_3R_105()) this.jj_scanpos = xsp;
/* 2158 */     if (jj_scan_token(9)) return true;
/* 2159 */     return false;
/*      */   }
/*      */   
/*      */   private boolean jj_3R_104() {
/* 2163 */     if (jj_3R_36()) return true;
/* 2164 */     return false;
/*      */   }
/*      */   
/*      */   private boolean jj_3R_29() {
/* 2168 */     if (jj_3R_34()) return true;
/*      */     Token xsp;
/*      */     do {
/* 2171 */       xsp = this.jj_scanpos;
/* 2172 */     } while (!jj_3R_35()); this.jj_scanpos = xsp;
/*      */     
/* 2174 */     return false;
/*      */   }
/*      */   
/*      */   private boolean jj_3_5() {
/* 2178 */     if (jj_scan_token(48)) return true;
/* 2179 */     if (jj_3R_22()) return true;
/* 2180 */     if (jj_scan_token(22)) return true;
/* 2181 */     return false;
/*      */   }
/*      */   
/*      */   private boolean jj_3R_98() {
/* 2185 */     if (jj_scan_token(20)) { return true;
/*      */     }
/* 2187 */     Token xsp = this.jj_scanpos;
/* 2188 */     if (jj_3R_104()) this.jj_scanpos = xsp;
/* 2189 */     if (jj_scan_token(21)) return true;
/* 2190 */     return false;
/*      */   }
/*      */   
/*      */   private boolean jj_3R_39() {
/* 2194 */     if (jj_3R_38()) return true;
/*      */     Token xsp;
/*      */     do {
/* 2197 */       xsp = this.jj_scanpos;
/* 2198 */     } while (!jj_3R_43()); this.jj_scanpos = xsp;
/*      */     
/* 2200 */     return false;
/*      */   }
/*      */   
/*      */   private boolean jj_3R_31() {
/* 2204 */     if (jj_3R_36()) return true;
/*      */     Token xsp;
/*      */     do {
/* 2207 */       xsp = this.jj_scanpos;
/* 2208 */     } while (!jj_3R_37()); this.jj_scanpos = xsp;
/*      */     
/* 2210 */     return false;
/*      */   }
/*      */   
/*      */   private boolean jj_3R_22() {
/* 2214 */     if (jj_3R_29()) return true;
/*      */     Token xsp;
/*      */     do {
/* 2217 */       xsp = this.jj_scanpos;
/* 2218 */     } while (!jj_3_5()); this.jj_scanpos = xsp;
/*      */     
/* 2220 */     return false;
/*      */   }
/*      */   
/*      */   private boolean jj_3_3() {
/* 2224 */     if (jj_3R_21()) return true;
/* 2225 */     return false;
/*      */   }
/*      */   
/*      */   private boolean jj_3R_25() {
/* 2229 */     if (jj_scan_token(8)) { return true;
/*      */     }
/* 2231 */     Token xsp = this.jj_scanpos;
/* 2232 */     if (jj_3R_31()) this.jj_scanpos = xsp;
/* 2233 */     if (jj_scan_token(9)) return true;
/* 2234 */     return false;
/*      */   }
/*      */   
/*      */   private boolean jj_3_4() {
/* 2238 */     if (jj_3R_21()) return true;
/* 2239 */     return false;
/*      */   }
/*      */   
/*      */   private boolean jj_3R_24() {
/* 2243 */     if (jj_scan_token(56)) return true;
/* 2244 */     if (jj_scan_token(22)) return true;
/* 2245 */     return false;
/*      */   }
/*      */   
/*      */   private boolean jj_3_7()
/*      */   {
/* 2250 */     Token xsp = this.jj_scanpos;
/* 2251 */     if (jj_3R_24()) this.jj_scanpos = xsp;
/* 2252 */     if (jj_scan_token(56)) return true;
/* 2253 */     if (jj_scan_token(18)) return true;
/* 2254 */     return false;
/*      */   }
/*      */   
/*      */   private boolean jj_3R_33() {
/* 2258 */     if (jj_scan_token(18)) { return true;
/*      */     }
/* 2260 */     Token xsp = this.jj_scanpos;
/* 2261 */     if (jj_3R_39()) this.jj_scanpos = xsp;
/* 2262 */     if (jj_scan_token(19)) return true;
/* 2263 */     return false;
/*      */   }
/*      */   
/*      */   private boolean jj_3R_89() {
/* 2267 */     if (jj_3R_99()) return true;
/* 2268 */     return false;
/*      */   }
/*      */   
/*      */   private boolean jj_3R_88() {
/* 2272 */     if (jj_3R_98()) return true;
/* 2273 */     return false;
/*      */   }
/*      */   
/*      */   private boolean jj_3R_23() {
/* 2277 */     if (jj_scan_token(18)) return true;
/* 2278 */     if (jj_3R_27()) return true;
/* 2279 */     if (jj_scan_token(55)) { return true;
/*      */     }
/* 2281 */     Token xsp = this.jj_scanpos;
/* 2282 */     if (jj_3_4()) {
/* 2283 */       this.jj_scanpos = xsp;
/* 2284 */       if (jj_3R_30()) return true;
/*      */     }
/* 2286 */     if (jj_scan_token(19)) return true;
/* 2287 */     return false;
/*      */   }
/*      */   
/*      */   private boolean jj_3_8() {
/* 2291 */     if (jj_3R_25()) return true;
/* 2292 */     return false;
/*      */   }
/*      */   
/*      */   private boolean jj_3R_87() {
/* 2296 */     if (jj_3R_38()) return true;
/* 2297 */     return false;
/*      */   }
/*      */   
/*      */   private boolean jj_3R_86() {
/* 2301 */     if (jj_3R_97()) return true;
/* 2302 */     return false;
/*      */   }
/*      */   
/*      */   private boolean jj_3R_85() {
/* 2306 */     if (jj_scan_token(18)) return true;
/* 2307 */     if (jj_3R_36()) return true;
/* 2308 */     return false;
/*      */   }
/*      */   
/*      */   private boolean jj_3_6() {
/* 2312 */     if (jj_3R_23()) return true;
/* 2313 */     return false;
/*      */   }
/*      */   
/*      */   private boolean jj_3R_77()
/*      */   {
/* 2318 */     Token xsp = this.jj_scanpos;
/* 2319 */     if (jj_3_6()) {
/* 2320 */       this.jj_scanpos = xsp;
/* 2321 */       if (jj_3R_85()) {
/* 2322 */         this.jj_scanpos = xsp;
/* 2323 */         if (jj_3R_86()) {
/* 2324 */           this.jj_scanpos = xsp;
/* 2325 */           if (jj_3R_87()) {
/* 2326 */             this.jj_scanpos = xsp;
/* 2327 */             if (jj_3_8()) {
/* 2328 */               this.jj_scanpos = xsp;
/* 2329 */               if (jj_3R_88()) {
/* 2330 */                 this.jj_scanpos = xsp;
/* 2331 */                 if (jj_3R_89()) return true;
/*      */               }
/*      */             }
/*      */           }
/*      */         }
/*      */       }
/*      */     }
/* 2338 */     return false;
/*      */   }
/*      */   
/*      */   private boolean jj_3R_32() {
/* 2342 */     if (jj_3R_38()) return true;
/* 2343 */     return false;
/*      */   }
/*      */   
/*      */   private boolean jj_3R_27()
/*      */   {
/* 2348 */     Token xsp = this.jj_scanpos;
/* 2349 */     if (jj_3R_32()) {
/* 2350 */       this.jj_scanpos = xsp;
/* 2351 */       if (jj_3R_33()) return true;
/*      */     }
/* 2353 */     return false;
/*      */   }
/*      */   
/*      */   private boolean jj_3_1() {
/* 2357 */     if (jj_scan_token(54)) return true;
/* 2358 */     if (jj_3R_20()) return true;
/* 2359 */     return false;
/*      */   }
/*      */   
/*      */   private boolean jj_3R_106() {
/* 2363 */     if (jj_scan_token(18)) return true;
/* 2364 */     return false;
/*      */   }
/*      */   
/*      */   private boolean jj_3R_21() {
/* 2368 */     if (jj_3R_27()) return true;
/* 2369 */     if (jj_scan_token(55)) { return true;
/*      */     }
/* 2371 */     Token xsp = this.jj_scanpos;
/* 2372 */     if (jj_3_3()) {
/* 2373 */       this.jj_scanpos = xsp;
/* 2374 */       if (jj_3R_28()) return true;
/*      */     }
/* 2376 */     return false;
/*      */   }
/*      */   
/*      */   private boolean jj_3R_46() {
/* 2380 */     if (jj_scan_token(23)) return true;
/* 2381 */     return false;
/*      */   }
/*      */   
/*      */   private boolean jj_3R_91() {
/* 2385 */     if (jj_scan_token(20)) return true;
/* 2386 */     return false;
/*      */   }
/*      */   
/*      */   private boolean jj_3R_26() {
/* 2390 */     if (jj_3R_22()) return true;
/*      */     Token xsp;
/*      */     do {
/* 2393 */       xsp = this.jj_scanpos;
/* 2394 */     } while (!jj_3_1()); this.jj_scanpos = xsp;
/*      */     
/* 2396 */     return false;
/*      */   }
/*      */   
/*      */   private boolean jj_3R_79() {
/* 2400 */     if (jj_3R_91()) return true;
/* 2401 */     return false;
/*      */   }
/*      */   
/*      */   private boolean jj_3_2() {
/* 2405 */     if (jj_3R_21()) return true;
/* 2406 */     return false;
/*      */   }
/*      */   
/*      */   private boolean jj_3R_20()
/*      */   {
/* 2411 */     Token xsp = this.jj_scanpos;
/* 2412 */     if (jj_3_2()) {
/* 2413 */       this.jj_scanpos = xsp;
/* 2414 */       if (jj_3R_26()) return true;
/*      */     }
/* 2416 */     return false;
/*      */   }
/*      */   
/*      */   private boolean jj_3R_90() {
/* 2420 */     if (jj_scan_token(17)) return true;
/* 2421 */     return false;
/*      */   }
/*      */   
/*      */   private boolean jj_3R_42() {
/* 2425 */     if (jj_3R_20()) return true;
/*      */     Token xsp;
/*      */     do {
/* 2428 */       xsp = this.jj_scanpos;
/* 2429 */     } while (!jj_3R_46()); this.jj_scanpos = xsp;
/*      */     
/* 2431 */     return false;
/*      */   }
/*      */   
/*      */   private boolean jj_3R_78() {
/* 2435 */     if (jj_3R_90()) return true;
/* 2436 */     return false;
/*      */   }
/*      */   
/*      */   private boolean jj_3R_75()
/*      */   {
/* 2441 */     Token xsp = this.jj_scanpos;
/* 2442 */     if (jj_3R_78()) {
/* 2443 */       this.jj_scanpos = xsp;
/* 2444 */       if (jj_3R_79()) return true;
/*      */     }
/* 2446 */     return false;
/*      */   }
/*      */   
/*      */   private boolean jj_3R_36() {
/* 2450 */     if (jj_3R_42()) return true;
/* 2451 */     return false;
/*      */   }
/*      */   
/*      */   private boolean jj_3R_72() {
/* 2455 */     if (jj_3R_75()) return true;
/* 2456 */     return false;
/*      */   }
/*      */   
/*      */   private boolean jj_3R_74() {
/* 2460 */     if (jj_3R_77()) return true;
/* 2461 */     return false;
/*      */   }
/*      */   
/*      */   private boolean jj_3R_71()
/*      */   {
/* 2466 */     Token xsp = this.jj_scanpos;
/* 2467 */     if (jj_3R_73()) {
/* 2468 */       this.jj_scanpos = xsp;
/* 2469 */       if (jj_3R_74()) return true;
/*      */     }
/* 2471 */     return false;
/*      */   }
/*      */   
/*      */   private boolean jj_3R_73() {
/* 2475 */     if (jj_3R_76()) return true;
/* 2476 */     return false;
/*      */   }
/*      */   
/*      */   private boolean jj_3R_70() {
/* 2480 */     if (jj_3R_71()) return true;
/*      */     Token xsp;
/*      */     do {
/* 2483 */       xsp = this.jj_scanpos;
/* 2484 */     } while (!jj_3R_72()); this.jj_scanpos = xsp;
/*      */     
/* 2486 */     return false;
/*      */   }
/*      */   
/*      */   private boolean jj_3R_96() {
/* 2490 */     if (jj_scan_token(16)) return true;
/* 2491 */     return false;
/*      */   }
/*      */   
/*      */   private boolean jj_3R_66() {
/* 2495 */     if (jj_3R_70()) return true;
/* 2496 */     return false;
/*      */   }
/*      */   
/*      */   private boolean jj_3R_65() {
/* 2500 */     if (jj_scan_token(43)) return true;
/* 2501 */     if (jj_3R_59()) return true;
/* 2502 */     return false;
/*      */   }
/*      */   
/*      */   private boolean jj_3R_64()
/*      */   {
/* 2507 */     Token xsp = this.jj_scanpos;
/* 2508 */     if (jj_scan_token(37)) {
/* 2509 */       this.jj_scanpos = xsp;
/* 2510 */       if (jj_scan_token(38)) return true;
/*      */     }
/* 2512 */     if (jj_3R_59()) return true;
/* 2513 */     return false;
/*      */   }
/*      */   
/*      */   private boolean jj_3R_59()
/*      */   {
/* 2518 */     Token xsp = this.jj_scanpos;
/* 2519 */     if (jj_3R_63()) {
/* 2520 */       this.jj_scanpos = xsp;
/* 2521 */       if (jj_3R_64()) {
/* 2522 */         this.jj_scanpos = xsp;
/* 2523 */         if (jj_3R_65()) {
/* 2524 */           this.jj_scanpos = xsp;
/* 2525 */           if (jj_3R_66()) return true;
/*      */         }
/*      */       }
/*      */     }
/* 2529 */     return false;
/*      */   }
/*      */   
/*      */   private boolean jj_3R_63() {
/* 2533 */     if (jj_scan_token(47)) return true;
/* 2534 */     if (jj_3R_59()) return true;
/* 2535 */     return false;
/*      */   }
/*      */   
/*      */   private boolean jj_3R_95() {
/* 2539 */     if (jj_scan_token(13)) return true;
/* 2540 */     return false;
/*      */   }
/*      */   
/*      */   private boolean jj_3R_69()
/*      */   {
/* 2545 */     Token xsp = this.jj_scanpos;
/* 2546 */     if (jj_scan_token(51)) {
/* 2547 */       this.jj_scanpos = xsp;
/* 2548 */       if (jj_scan_token(52)) return true;
/*      */     }
/* 2550 */     return false;
/*      */   }
/*      */   
/*      */   private boolean jj_3R_94() {
/* 2554 */     if (jj_scan_token(10)) return true;
/* 2555 */     return false;
/*      */   }
/*      */   
/*      */   private boolean jj_3R_68()
/*      */   {
/* 2560 */     Token xsp = this.jj_scanpos;
/* 2561 */     if (jj_scan_token(49)) {
/* 2562 */       this.jj_scanpos = xsp;
/* 2563 */       if (jj_scan_token(50)) return true;
/*      */     }
/* 2565 */     return false;
/*      */   }
/*      */   
/*      */   private boolean jj_3R_60()
/*      */   {
/* 2570 */     Token xsp = this.jj_scanpos;
/* 2571 */     if (jj_3R_67()) {
/* 2572 */       this.jj_scanpos = xsp;
/* 2573 */       if (jj_3R_68()) {
/* 2574 */         this.jj_scanpos = xsp;
/* 2575 */         if (jj_3R_69()) return true;
/*      */       }
/*      */     }
/* 2578 */     return false;
/*      */   }
/*      */   
/*      */   private boolean jj_3R_67() {
/* 2582 */     if (jj_scan_token(45)) return true;
/* 2583 */     return false;
/*      */   }
/*      */   
/*      */   private boolean jj_3R_57() {
/* 2587 */     if (jj_3R_59()) return true;
/*      */     Token xsp;
/*      */     do {
/* 2590 */       xsp = this.jj_scanpos;
/* 2591 */     } while (!jj_3R_60()); this.jj_scanpos = xsp;
/*      */     
/* 2593 */     return false;
/*      */   }
/*      */   
/*      */   private boolean jj_3R_93() {
/* 2597 */     if (jj_scan_token(11)) return true;
/* 2598 */     return false;
/*      */   }
/*      */   
/*      */   private boolean jj_3R_62() {
/* 2602 */     if (jj_scan_token(47)) return true;
/* 2603 */     return false;
/*      */   }
/*      */   
/*      */   private boolean jj_3R_101() {
/* 2607 */     if (jj_scan_token(15)) return true;
/* 2608 */     return false;
/*      */   }
/*      */   
/*      */   private boolean jj_3R_58()
/*      */   {
/* 2613 */     Token xsp = this.jj_scanpos;
/* 2614 */     if (jj_3R_61()) {
/* 2615 */       this.jj_scanpos = xsp;
/* 2616 */       if (jj_3R_62()) return true;
/*      */     }
/* 2618 */     return false;
/*      */   }
/*      */   
/*      */   private boolean jj_3R_61() {
/* 2622 */     if (jj_scan_token(46)) return true;
/* 2623 */     return false;
/*      */   }
/*      */   
/*      */   private boolean jj_3R_100() {
/* 2627 */     if (jj_scan_token(14)) return true;
/* 2628 */     return false;
/*      */   }
/*      */   
/*      */   private boolean jj_3R_92()
/*      */   {
/* 2633 */     Token xsp = this.jj_scanpos;
/* 2634 */     if (jj_3R_100()) {
/* 2635 */       this.jj_scanpos = xsp;
/* 2636 */       if (jj_3R_101()) return true;
/*      */     }
/* 2638 */     return false;
/*      */   }
/*      */   
/*      */   private boolean jj_3R_51() {
/* 2642 */     if (jj_3R_57()) return true;
/*      */     Token xsp;
/*      */     do {
/* 2645 */       xsp = this.jj_scanpos;
/* 2646 */     } while (!jj_3R_58()); this.jj_scanpos = xsp;
/*      */     
/* 2648 */     return false;
/*      */   }
/*      */   
/*      */   private boolean jj_3R_84() {
/* 2652 */     if (jj_3R_96()) return true;
/* 2653 */     return false;
/*      */   }
/*      */   
/*      */   private boolean jj_3R_83() {
/* 2657 */     if (jj_3R_95()) return true;
/* 2658 */     return false;
/*      */   }
/*      */   
/*      */   private boolean jj_3R_52() {
/* 2662 */     if (jj_scan_token(53)) return true;
/* 2663 */     return false;
/*      */   }
/*      */   
/*      */   private boolean jj_3R_82() {
/* 2667 */     if (jj_3R_94()) return true;
/* 2668 */     return false;
/*      */   }
/*      */   
/*      */   private boolean jj_3R_81() {
/* 2672 */     if (jj_3R_93()) return true;
/* 2673 */     return false;
/*      */   }
/*      */   
/*      */   private boolean jj_3R_102() {
/* 2677 */     if (jj_scan_token(22)) return true;
/* 2678 */     return false;
/*      */   }
/*      */   
/*      */   private boolean jj_3R_76()
/*      */   {
/* 2683 */     Token xsp = this.jj_scanpos;
/* 2684 */     if (jj_3R_80()) {
/* 2685 */       this.jj_scanpos = xsp;
/* 2686 */       if (jj_3R_81()) {
/* 2687 */         this.jj_scanpos = xsp;
/* 2688 */         if (jj_3R_82()) {
/* 2689 */           this.jj_scanpos = xsp;
/* 2690 */           if (jj_3R_83()) {
/* 2691 */             this.jj_scanpos = xsp;
/* 2692 */             if (jj_3R_84()) return true;
/*      */           }
/*      */         }
/*      */       }
/*      */     }
/* 2697 */     return false;
/*      */   }
/*      */   
/*      */   private boolean jj_3R_80() {
/* 2701 */     if (jj_3R_92()) return true;
/* 2702 */     return false;
/*      */   }
/*      */   
/*      */   private boolean jj_3R_47() {
/* 2706 */     if (jj_3R_51()) return true;
/*      */     Token xsp;
/*      */     do {
/* 2709 */       xsp = this.jj_scanpos;
/* 2710 */     } while (!jj_3R_52()); this.jj_scanpos = xsp;
/*      */     
/* 2712 */     return false;
/*      */   }
/*      */   
/*      */   private boolean jj_3R_103() {
/* 2716 */     if (jj_3R_106()) return true;
/* 2717 */     return false;
/*      */   }
/*      */   
/*      */   private boolean jj_3R_56()
/*      */   {
/* 2722 */     Token xsp = this.jj_scanpos;
/* 2723 */     if (jj_scan_token(29)) {
/* 2724 */       this.jj_scanpos = xsp;
/* 2725 */       if (jj_scan_token(30)) return true;
/*      */     }
/* 2727 */     return false;
/*      */   }
/*      */   
/*      */   private boolean jj_3R_55()
/*      */   {
/* 2732 */     Token xsp = this.jj_scanpos;
/* 2733 */     if (jj_scan_token(31)) {
/* 2734 */       this.jj_scanpos = xsp;
/* 2735 */       if (jj_scan_token(32)) return true;
/*      */     }
/* 2737 */     return false;
/*      */   }
/*      */   
/*      */   private boolean jj_3R_54()
/*      */   {
/* 2742 */     Token xsp = this.jj_scanpos;
/* 2743 */     if (jj_scan_token(25)) {
/* 2744 */       this.jj_scanpos = xsp;
/* 2745 */       if (jj_scan_token(26)) return true;
/*      */     }
/* 2747 */     return false;
/*      */   }
/*      */   
/*      */   private boolean jj_3R_48()
/*      */   {
/* 2752 */     Token xsp = this.jj_scanpos;
/* 2753 */     if (jj_3R_53()) {
/* 2754 */       this.jj_scanpos = xsp;
/* 2755 */       if (jj_3R_54()) {
/* 2756 */         this.jj_scanpos = xsp;
/* 2757 */         if (jj_3R_55()) {
/* 2758 */           this.jj_scanpos = xsp;
/* 2759 */           if (jj_3R_56()) return true;
/*      */         }
/*      */       }
/*      */     }
/* 2763 */     return false;
/*      */   }
/*      */   
/*      */   private boolean jj_3R_53()
/*      */   {
/* 2768 */     Token xsp = this.jj_scanpos;
/* 2769 */     if (jj_scan_token(27)) {
/* 2770 */       this.jj_scanpos = xsp;
/* 2771 */       if (jj_scan_token(28)) return true;
/*      */     }
/* 2773 */     return false;
/*      */   }
/*      */   
/*      */   private boolean jj_3R_97() {
/* 2777 */     if (jj_scan_token(56)) { return true;
/*      */     }
/* 2779 */     Token xsp = this.jj_scanpos;
/* 2780 */     if (jj_3R_102()) this.jj_scanpos = xsp;
/* 2781 */     if (jj_3R_103()) return true;
/*      */     do {
/* 2783 */       xsp = this.jj_scanpos;
/* 2784 */     } while (!jj_3R_103()); this.jj_scanpos = xsp;
/*      */     
/* 2786 */     return false;
/*      */   }
/*      */   
/*      */   private boolean jj_3R_44() {
/* 2790 */     if (jj_3R_47()) return true;
/*      */     Token xsp;
/*      */     do {
/* 2793 */       xsp = this.jj_scanpos;
/* 2794 */     } while (!jj_3R_48()); this.jj_scanpos = xsp;
/*      */     
/* 2796 */     return false;
/*      */   }
/*      */   
/*      */   private boolean jj_3R_50()
/*      */   {
/* 2801 */     Token xsp = this.jj_scanpos;
/* 2802 */     if (jj_scan_token(35)) {
/* 2803 */       this.jj_scanpos = xsp;
/* 2804 */       if (jj_scan_token(36)) return true;
/*      */     }
/* 2806 */     return false;
/*      */   }
/*      */   
/*      */   private boolean jj_3R_45()
/*      */   {
/* 2811 */     Token xsp = this.jj_scanpos;
/* 2812 */     if (jj_3R_49()) {
/* 2813 */       this.jj_scanpos = xsp;
/* 2814 */       if (jj_3R_50()) return true;
/*      */     }
/* 2816 */     return false;
/*      */   }
/*      */   
/*      */   private boolean jj_3R_49()
/*      */   {
/* 2821 */     Token xsp = this.jj_scanpos;
/* 2822 */     if (jj_scan_token(33)) {
/* 2823 */       this.jj_scanpos = xsp;
/* 2824 */       if (jj_scan_token(34)) return true;
/*      */     }
/* 2826 */     return false;
/*      */   }
/*      */   
/*      */   private boolean jj_3R_28() {
/* 2830 */     if (jj_3R_22()) return true;
/* 2831 */     return false;
/*      */   }
/*      */   
/*      */   private boolean jj_3R_38() {
/* 2835 */     if (jj_scan_token(56)) return true;
/* 2836 */     return false;
/*      */   }
/*      */   
/*      */ 
/*      */ 
/*      */ 
/*      */ 
/*      */ 
/*      */ 
/*      */ 
/*      */ 
/*      */ 
/*      */ 
/*      */ 
/* 2850 */   private final int[] jj_la1 = new int[52];
/*      */   private static int[] jj_la1_0;
/*      */   private static int[] jj_la1_1;
/*      */   
/* 2854 */   static { jj_la1_init_0();
/* 2855 */     jj_la1_init_1();
/*      */   }
/*      */   
/* 2858 */   private static void jj_la1_init_0() { jj_la1_0 = new int[] { 14, 14, 8388608, 1436928, 1436928, 16777216, 0, 262144, 1436928, 262144, 0, 0, 0, 0, 0, 0, 0, 0, -33554432, 402653184, 100663296, Integer.MIN_VALUE, 1610612736, -33554432, 0, 0, 0, 0, 0, 0, 0, 0, 1436928, 1179648, 1436928, 1179648, 262144, 16777216, 1436928, 262144, 0, 1048832, 16777216, 1436928, 16777216, 1436928, 16777216, 1436928, 4194304, 262144, 125952, 49152 }; }
/*      */   
/*      */ 
/* 2861 */   private static void jj_la1_init_1() { jj_la1_1 = new int[] { 0, 0, 0, 16812128, 16812128, 0, 16777216, 16777216, 16812128, 0, 1536, 1536, 384, 384, 30, 6, 24, 30, 1, 0, 0, 1, 0, 1, 2097152, 49152, 49152, 1974272, 393216, 1572864, 1974272, 96, 16812128, 0, 16777216, 0, 0, 0, 16812128, 0, 16777216, 0, 0, 16812128, 0, 16812128, 0, 16812128, 0, 0, 0, 0 }; }
/*      */   
/* 2863 */   private final JJCalls[] jj_2_rtns = new JJCalls[8];
/* 2864 */   private boolean jj_rescan = false;
/* 2865 */   private int jj_gc = 0;
/*      */   
/*      */ 
/*      */ 
/* 2869 */   public ELParser(java.io.InputStream stream) { this(stream, null); }
/*      */   
/*      */   public ELParser(java.io.InputStream stream, String encoding) {
/*      */     try {
/* 2873 */       this.jj_input_stream = new SimpleCharStream(stream, encoding, 1, 1); } catch (java.io.UnsupportedEncodingException e) { throw new RuntimeException(e); }
/* 2874 */     this.token_source = new ELParserTokenManager(this.jj_input_stream);
/* 2875 */     this.token = new Token();
/* 2876 */     this.jj_ntk = -1;
/* 2877 */     this.jj_gen = 0;
/* 2878 */     for (int i = 0; i < 52; i++) this.jj_la1[i] = -1;
/* 2879 */     for (int i = 0; i < this.jj_2_rtns.length; i++) { this.jj_2_rtns[i] = new JJCalls();
/*      */     }
/*      */   }
/*      */   
/*      */ 
/* 2884 */   public void ReInit(java.io.InputStream stream) { ReInit(stream, null); }
/*      */   
/*      */   public void ReInit(java.io.InputStream stream, String encoding) {
/*      */     try {
/* 2888 */       this.jj_input_stream.ReInit(stream, encoding, 1, 1); } catch (java.io.UnsupportedEncodingException e) { throw new RuntimeException(e); }
/* 2889 */     this.token_source.ReInit(this.jj_input_stream);
/* 2890 */     this.token = new Token();
/* 2891 */     this.jj_ntk = -1;
/* 2892 */     this.jjtree.reset();
/* 2893 */     this.jj_gen = 0;
/* 2894 */     for (int i = 0; i < 52; i++) this.jj_la1[i] = -1;
/* 2895 */     for (int i = 0; i < this.jj_2_rtns.length; i++) this.jj_2_rtns[i] = new JJCalls();
/*      */   }
/*      */   
/*      */   public ELParser(java.io.Reader stream)
/*      */   {
/* 2900 */     this.jj_input_stream = new SimpleCharStream(stream, 1, 1);
/* 2901 */     this.token_source = new ELParserTokenManager(this.jj_input_stream);
/* 2902 */     this.token = new Token();
/* 2903 */     this.jj_ntk = -1;
/* 2904 */     this.jj_gen = 0;
/* 2905 */     for (int i = 0; i < 52; i++) this.jj_la1[i] = -1;
/* 2906 */     for (int i = 0; i < this.jj_2_rtns.length; i++) this.jj_2_rtns[i] = new JJCalls();
/*      */   }
/*      */   
/*      */   public void ReInit(java.io.Reader stream)
/*      */   {
/* 2911 */     this.jj_input_stream.ReInit(stream, 1, 1);
/* 2912 */     this.token_source.ReInit(this.jj_input_stream);
/* 2913 */     this.token = new Token();
/* 2914 */     this.jj_ntk = -1;
/* 2915 */     this.jjtree.reset();
/* 2916 */     this.jj_gen = 0;
/* 2917 */     for (int i = 0; i < 52; i++) this.jj_la1[i] = -1;
/* 2918 */     for (int i = 0; i < this.jj_2_rtns.length; i++) this.jj_2_rtns[i] = new JJCalls();
/*      */   }
/*      */   
/*      */   public ELParser(ELParserTokenManager tm)
/*      */   {
/* 2923 */     this.token_source = tm;
/* 2924 */     this.token = new Token();
/* 2925 */     this.jj_ntk = -1;
/* 2926 */     this.jj_gen = 0;
/* 2927 */     for (int i = 0; i < 52; i++) this.jj_la1[i] = -1;
/* 2928 */     for (int i = 0; i < this.jj_2_rtns.length; i++) this.jj_2_rtns[i] = new JJCalls();
/*      */   }
/*      */   
/*      */   public void ReInit(ELParserTokenManager tm)
/*      */   {
/* 2933 */     this.token_source = tm;
/* 2934 */     this.token = new Token();
/* 2935 */     this.jj_ntk = -1;
/* 2936 */     this.jjtree.reset();
/* 2937 */     this.jj_gen = 0;
/* 2938 */     for (int i = 0; i < 52; i++) this.jj_la1[i] = -1;
/* 2939 */     for (int i = 0; i < this.jj_2_rtns.length; i++) this.jj_2_rtns[i] = new JJCalls();
/*      */   }
/*      */   
/*      */   private Token jj_consume_token(int kind) throws ParseException {
/*      */     Token oldToken;
/* 2944 */     if ((oldToken = this.token).next != null) this.token = this.token.next; else
/* 2945 */       this.token = (this.token.next = this.token_source.getNextToken());
/* 2946 */     this.jj_ntk = -1;
/* 2947 */     if (this.token.kind == kind) {
/* 2948 */       this.jj_gen += 1;
/* 2949 */       if (++this.jj_gc > 100) {
/* 2950 */         this.jj_gc = 0;
/* 2951 */         for (int i = 0; i < this.jj_2_rtns.length; i++) {
/* 2952 */           JJCalls c = this.jj_2_rtns[i];
/* 2953 */           while (c != null) {
/* 2954 */             if (c.gen < this.jj_gen) c.first = null;
/* 2955 */             c = c.next;
/*      */           }
/*      */         }
/*      */       }
/* 2959 */       return this.token;
/*      */     }
/* 2961 */     this.token = oldToken;
/* 2962 */     this.jj_kind = kind;
/* 2963 */     throw generateParseException();
/*      */   }
/*      */   
/*      */   static final class JJCalls {
/*      */     int gen;
/*      */     Token first;
/*      */     int arg;
/*      */     JJCalls next;
/*      */   }
/*      */   
/* 2973 */   private static final class LookaheadSuccess extends Error { public synchronized Throwable fillInStackTrace() { return this; }
/*      */   }
/*      */   
/* 2976 */   private final LookaheadSuccess jj_ls = new LookaheadSuccess(null);
/*      */   
/* 2978 */   private boolean jj_scan_token(int kind) { if (this.jj_scanpos == this.jj_lastpos) {
/* 2979 */       this.jj_la -= 1;
/* 2980 */       if (this.jj_scanpos.next == null) {
/* 2981 */         this.jj_lastpos = (this.jj_scanpos = this.jj_scanpos.next = this.token_source.getNextToken());
/*      */       } else {
/* 2983 */         this.jj_lastpos = (this.jj_scanpos = this.jj_scanpos.next);
/*      */       }
/*      */     } else {
/* 2986 */       this.jj_scanpos = this.jj_scanpos.next;
/*      */     }
/* 2988 */     if (this.jj_rescan) {
/* 2989 */       int i = 0; for (Token tok = this.token; 
/* 2990 */           (tok != null) && (tok != this.jj_scanpos); tok = tok.next) i++;
/* 2991 */       if (tok != null) jj_add_error_token(kind, i);
/*      */     }
/* 2993 */     if (this.jj_scanpos.kind != kind) return true;
/* 2994 */     if ((this.jj_la == 0) && (this.jj_scanpos == this.jj_lastpos)) throw this.jj_ls;
/* 2995 */     return false;
/*      */   }
/*      */   
/*      */ 
/*      */   public final Token getNextToken()
/*      */   {
/* 3001 */     if (this.token.next != null) this.token = this.token.next; else
/* 3002 */       this.token = (this.token.next = this.token_source.getNextToken());
/* 3003 */     this.jj_ntk = -1;
/* 3004 */     this.jj_gen += 1;
/* 3005 */     return this.token;
/*      */   }
/*      */   
/*      */   public final Token getToken(int index)
/*      */   {
/* 3010 */     Token t = this.token;
/* 3011 */     for (int i = 0; i < index; i++) {
/* 3012 */       if (t.next != null) t = t.next; else
/* 3013 */         t = t.next = this.token_source.getNextToken();
/*      */     }
/* 3015 */     return t;
/*      */   }
/*      */   
/*      */   private int jj_ntk() {
/* 3019 */     if ((this.jj_nt = this.token.next) == null) {
/* 3020 */       return this.jj_ntk = (this.token.next = this.token_source.getNextToken()).kind;
/*      */     }
/* 3022 */     return this.jj_ntk = this.jj_nt.kind;
/*      */   }
/*      */   
/* 3025 */   private List<int[]> jj_expentries = new java.util.ArrayList();
/*      */   private int[] jj_expentry;
/* 3027 */   private int jj_kind = -1;
/* 3028 */   private int[] jj_lasttokens = new int[100];
/*      */   private int jj_endpos;
/*      */   
/*      */   private void jj_add_error_token(int kind, int pos) {
/* 3032 */     if (pos >= 100) return;
/* 3033 */     if (pos == this.jj_endpos + 1) {
/* 3034 */       this.jj_lasttokens[(this.jj_endpos++)] = kind;
/* 3035 */     } else if (this.jj_endpos != 0) {
/* 3036 */       this.jj_expentry = new int[this.jj_endpos];
/* 3037 */       for (int i = 0; i < this.jj_endpos; i++) {
/* 3038 */         this.jj_expentry[i] = this.jj_lasttokens[i];
/*      */       }
/* 3040 */       for (java.util.Iterator<?> it = this.jj_expentries.iterator(); it.hasNext();) {
/* 3041 */         int[] oldentry = (int[])it.next();
/* 3042 */         if (oldentry.length == this.jj_expentry.length) {
/* 3043 */           for (int i = 0;; i++) { if (i >= this.jj_expentry.length) break label163;
/* 3044 */             if (oldentry[i] != this.jj_expentry[i]) {
/*      */               break;
/*      */             }
/*      */           }
/* 3048 */           this.jj_expentries.add(this.jj_expentry);
/* 3049 */           break;
/*      */         } }
/*      */       label163:
/* 3052 */       if (pos != 0) this.jj_lasttokens[((this.jj_endpos = pos) - 1)] = kind;
/*      */     }
/*      */   }
/*      */   
/*      */   public ParseException generateParseException()
/*      */   {
/* 3058 */     this.jj_expentries.clear();
/* 3059 */     boolean[] la1tokens = new boolean[62];
/* 3060 */     if (this.jj_kind >= 0) {
/* 3061 */       la1tokens[this.jj_kind] = true;
/* 3062 */       this.jj_kind = -1;
/*      */     }
/* 3064 */     for (int i = 0; i < 52; i++) {
/* 3065 */       if (this.jj_la1[i] == this.jj_gen) {
/* 3066 */         for (int j = 0; j < 32; j++) {
/* 3067 */           if ((jj_la1_0[i] & 1 << j) != 0) {
/* 3068 */             la1tokens[j] = true;
/*      */           }
/* 3070 */           if ((jj_la1_1[i] & 1 << j) != 0) {
/* 3071 */             la1tokens[(32 + j)] = true;
/*      */           }
/*      */         }
/*      */       }
/*      */     }
/* 3076 */     for (int i = 0; i < 62; i++) {
/* 3077 */       if (la1tokens[i] != 0) {
/* 3078 */         this.jj_expentry = new int[1];
/* 3079 */         this.jj_expentry[0] = i;
/* 3080 */         this.jj_expentries.add(this.jj_expentry);
/*      */       }
/*      */     }
/* 3083 */     this.jj_endpos = 0;
/* 3084 */     jj_rescan_token();
/* 3085 */     jj_add_error_token(0, 0);
/* 3086 */     int[][] exptokseq = new int[this.jj_expentries.size()][];
/* 3087 */     for (int i = 0; i < this.jj_expentries.size(); i++) {
/* 3088 */       exptokseq[i] = ((int[])this.jj_expentries.get(i));
/*      */     }
/* 3090 */     return new ParseException(this.token, exptokseq, tokenImage);
/*      */   }
/*      */   
/*      */ 
/*      */ 
/*      */ 
/*      */ 
/*      */ 
/*      */ 
/*      */ 
/*      */   private void jj_rescan_token()
/*      */   {
/* 3102 */     this.jj_rescan = true;
/* 3103 */     for (int i = 0; i < 8; i++) {
/*      */       try {
/* 3105 */         JJCalls p = this.jj_2_rtns[i];
/*      */         do {
/* 3107 */           if (p.gen > this.jj_gen) {
/* 3108 */             this.jj_la = p.arg;this.jj_lastpos = (this.jj_scanpos = p.first);
/* 3109 */             switch (i) {
/* 3110 */             case 0:  jj_3_1(); break;
/* 3111 */             case 1:  jj_3_2(); break;
/* 3112 */             case 2:  jj_3_3(); break;
/* 3113 */             case 3:  jj_3_4(); break;
/* 3114 */             case 4:  jj_3_5(); break;
/* 3115 */             case 5:  jj_3_6(); break;
/* 3116 */             case 6:  jj_3_7(); break;
/* 3117 */             case 7:  jj_3_8();
/*      */             }
/*      */           }
/* 3120 */           p = p.next;
/* 3121 */         } while (p != null);
/*      */       } catch (LookaheadSuccess localLookaheadSuccess) {}
/*      */     }
/* 3124 */     this.jj_rescan = false;
/*      */   }
/*      */   
/*      */   private void jj_save(int index, int xla) {
/* 3128 */     JJCalls p = this.jj_2_rtns[index];
/* 3129 */     while (p.gen > this.jj_gen) {
/* 3130 */       if (p.next == null) { p = p.next = new JJCalls(); break; }
/* 3131 */       p = p.next;
/*      */     }
/* 3133 */     p.gen = (this.jj_gen + xla - this.jj_la);p.first = this.token;p.arg = xla;
/*      */   }
/*      */   
/*      */   /* Error */
/*      */   public final void Boolean()
/*      */     throws ParseException
/*      */   {
/*      */     // Byte code:
/*      */     //   0: aload_0
/*      */     //   1: getfield 15	org/apache/el/parser/ELParser:jj_ntk	I
/*      */     //   4: iconst_m1
/*      */     //   5: if_icmpne +10 -> 15
/*      */     //   8: aload_0
/*      */     //   9: invokespecial 16	org/apache/el/parser/ELParser:jj_ntk	()I
/*      */     //   12: goto +7 -> 19
/*      */     //   15: aload_0
/*      */     //   16: getfield 15	org/apache/el/parser/ELParser:jj_ntk	I
/*      */     //   19: lookupswitch	default:+154->173, 14:+25->44, 15:+87->106
/*      */     //   44: new 152	org/apache/el/parser/AstTrue
/*      */     //   47: dup
/*      */     //   48: bipush 37
/*      */     //   50: invokespecial 153	org/apache/el/parser/AstTrue:<init>	(I)V
/*      */     //   53: astore_1
/*      */     //   54: iconst_1
/*      */     //   55: istore_2
/*      */     //   56: aload_0
/*      */     //   57: getfield 13	org/apache/el/parser/ELParser:jjtree	Lorg/apache/el/parser/JJTELParserState;
/*      */     //   60: aload_1
/*      */     //   61: invokevirtual 14	org/apache/el/parser/JJTELParserState:openNodeScope	(Lorg/apache/el/parser/Node;)V
/*      */     //   64: aload_0
/*      */     //   65: bipush 14
/*      */     //   67: invokespecial 22	org/apache/el/parser/ELParser:jj_consume_token	(I)Lorg/apache/el/parser/Token;
/*      */     //   70: pop
/*      */     //   71: iload_2
/*      */     //   72: ifeq +31 -> 103
/*      */     //   75: aload_0
/*      */     //   76: getfield 13	org/apache/el/parser/ELParser:jjtree	Lorg/apache/el/parser/JJTELParserState;
/*      */     //   79: aload_1
/*      */     //   80: iconst_1
/*      */     //   81: invokevirtual 24	org/apache/el/parser/JJTELParserState:closeNodeScope	(Lorg/apache/el/parser/Node;Z)V
/*      */     //   84: goto +19 -> 103
/*      */     //   87: astore_3
/*      */     //   88: iload_2
/*      */     //   89: ifeq +12 -> 101
/*      */     //   92: aload_0
/*      */     //   93: getfield 13	org/apache/el/parser/ELParser:jjtree	Lorg/apache/el/parser/JJTELParserState;
/*      */     //   96: aload_1
/*      */     //   97: iconst_1
/*      */     //   98: invokevirtual 24	org/apache/el/parser/JJTELParserState:closeNodeScope	(Lorg/apache/el/parser/Node;Z)V
/*      */     //   101: aload_3
/*      */     //   102: athrow
/*      */     //   103: goto +95 -> 198
/*      */     //   106: new 154	org/apache/el/parser/AstFalse
/*      */     //   109: dup
/*      */     //   110: bipush 38
/*      */     //   112: invokespecial 155	org/apache/el/parser/AstFalse:<init>	(I)V
/*      */     //   115: astore_3
/*      */     //   116: iconst_1
/*      */     //   117: istore 4
/*      */     //   119: aload_0
/*      */     //   120: getfield 13	org/apache/el/parser/ELParser:jjtree	Lorg/apache/el/parser/JJTELParserState;
/*      */     //   123: aload_3
/*      */     //   124: invokevirtual 14	org/apache/el/parser/JJTELParserState:openNodeScope	(Lorg/apache/el/parser/Node;)V
/*      */     //   127: aload_0
/*      */     //   128: bipush 15
/*      */     //   130: invokespecial 22	org/apache/el/parser/ELParser:jj_consume_token	(I)Lorg/apache/el/parser/Token;
/*      */     //   133: pop
/*      */     //   134: iload 4
/*      */     //   136: ifeq +34 -> 170
/*      */     //   139: aload_0
/*      */     //   140: getfield 13	org/apache/el/parser/ELParser:jjtree	Lorg/apache/el/parser/JJTELParserState;
/*      */     //   143: aload_3
/*      */     //   144: iconst_1
/*      */     //   145: invokevirtual 24	org/apache/el/parser/JJTELParserState:closeNodeScope	(Lorg/apache/el/parser/Node;Z)V
/*      */     //   148: goto +22 -> 170
/*      */     //   151: astore 5
/*      */     //   153: iload 4
/*      */     //   155: ifeq +12 -> 167
/*      */     //   158: aload_0
/*      */     //   159: getfield 13	org/apache/el/parser/ELParser:jjtree	Lorg/apache/el/parser/JJTELParserState;
/*      */     //   162: aload_3
/*      */     //   163: iconst_1
/*      */     //   164: invokevirtual 24	org/apache/el/parser/JJTELParserState:closeNodeScope	(Lorg/apache/el/parser/Node;Z)V
/*      */     //   167: aload 5
/*      */     //   169: athrow
/*      */     //   170: goto +28 -> 198
/*      */     //   173: aload_0
/*      */     //   174: getfield 17	org/apache/el/parser/ELParser:jj_la1	[I
/*      */     //   177: bipush 51
/*      */     //   179: aload_0
/*      */     //   180: getfield 18	org/apache/el/parser/ELParser:jj_gen	I
/*      */     //   183: iastore
/*      */     //   184: aload_0
/*      */     //   185: iconst_m1
/*      */     //   186: invokespecial 22	org/apache/el/parser/ELParser:jj_consume_token	(I)Lorg/apache/el/parser/Token;
/*      */     //   189: pop
/*      */     //   190: new 6	org/apache/el/parser/ParseException
/*      */     //   193: dup
/*      */     //   194: invokespecial 23	org/apache/el/parser/ParseException:<init>	()V
/*      */     //   197: athrow
/*      */     //   198: return
/*      */     // Line number table:
/*      */     //   Java source line #1918	-> byte code offset #0
/*      */     //   Java source line #1920	-> byte code offset #44
/*      */     //   Java source line #1921	-> byte code offset #54
/*      */     //   Java source line #1922	-> byte code offset #56
/*      */     //   Java source line #1924	-> byte code offset #64
/*      */     //   Java source line #1926	-> byte code offset #71
/*      */     //   Java source line #1927	-> byte code offset #75
/*      */     //   Java source line #1926	-> byte code offset #87
/*      */     //   Java source line #1927	-> byte code offset #92
/*      */     //   Java source line #1930	-> byte code offset #103
/*      */     //   Java source line #1932	-> byte code offset #106
/*      */     //   Java source line #1933	-> byte code offset #116
/*      */     //   Java source line #1934	-> byte code offset #119
/*      */     //   Java source line #1936	-> byte code offset #127
/*      */     //   Java source line #1938	-> byte code offset #134
/*      */     //   Java source line #1939	-> byte code offset #139
/*      */     //   Java source line #1938	-> byte code offset #151
/*      */     //   Java source line #1939	-> byte code offset #158
/*      */     //   Java source line #1942	-> byte code offset #170
/*      */     //   Java source line #1944	-> byte code offset #173
/*      */     //   Java source line #1945	-> byte code offset #184
/*      */     //   Java source line #1946	-> byte code offset #190
/*      */     //   Java source line #1948	-> byte code offset #198
/*      */     // Local variable table:
/*      */     //   start	length	slot	name	signature
/*      */     //   0	199	0	this	ELParser
/*      */     //   53	44	1	jjtn001	AstTrue
/*      */     //   55	34	2	jjtc001	boolean
/*      */     //   87	15	3	localObject1	Object
/*      */     //   115	48	3	jjtn002	AstFalse
/*      */     //   117	37	4	jjtc002	boolean
/*      */     //   151	17	5	localObject2	Object
/*      */     // Exception table:
/*      */     //   from	to	target	type
/*      */     //   64	71	87	finally
/*      */     //   127	134	151	finally
/*      */     //   151	153	151	finally
/*      */   }
/*      */   
/*      */   /* Error */
/*      */   public final void Null()
/*      */     throws ParseException
/*      */   {
/*      */     // Byte code:
/*      */     //   0: new 165	org/apache/el/parser/AstNull
/*      */     //   3: dup
/*      */     //   4: bipush 42
/*      */     //   6: invokespecial 166	org/apache/el/parser/AstNull:<init>	(I)V
/*      */     //   9: astore_1
/*      */     //   10: iconst_1
/*      */     //   11: istore_2
/*      */     //   12: aload_0
/*      */     //   13: getfield 13	org/apache/el/parser/ELParser:jjtree	Lorg/apache/el/parser/JJTELParserState;
/*      */     //   16: aload_1
/*      */     //   17: invokevirtual 14	org/apache/el/parser/JJTELParserState:openNodeScope	(Lorg/apache/el/parser/Node;)V
/*      */     //   20: aload_0
/*      */     //   21: bipush 16
/*      */     //   23: invokespecial 22	org/apache/el/parser/ELParser:jj_consume_token	(I)Lorg/apache/el/parser/Token;
/*      */     //   26: pop
/*      */     //   27: iload_2
/*      */     //   28: ifeq +31 -> 59
/*      */     //   31: aload_0
/*      */     //   32: getfield 13	org/apache/el/parser/ELParser:jjtree	Lorg/apache/el/parser/JJTELParserState;
/*      */     //   35: aload_1
/*      */     //   36: iconst_1
/*      */     //   37: invokevirtual 24	org/apache/el/parser/JJTELParserState:closeNodeScope	(Lorg/apache/el/parser/Node;Z)V
/*      */     //   40: goto +19 -> 59
/*      */     //   43: astore_3
/*      */     //   44: iload_2
/*      */     //   45: ifeq +12 -> 57
/*      */     //   48: aload_0
/*      */     //   49: getfield 13	org/apache/el/parser/ELParser:jjtree	Lorg/apache/el/parser/JJTELParserState;
/*      */     //   52: aload_1
/*      */     //   53: iconst_1
/*      */     //   54: invokevirtual 24	org/apache/el/parser/JJTELParserState:closeNodeScope	(Lorg/apache/el/parser/Node;Z)V
/*      */     //   57: aload_3
/*      */     //   58: athrow
/*      */     //   59: return
/*      */     // Line number table:
/*      */     //   Java source line #2019	-> byte code offset #0
/*      */     //   Java source line #2020	-> byte code offset #10
/*      */     //   Java source line #2021	-> byte code offset #12
/*      */     //   Java source line #2023	-> byte code offset #20
/*      */     //   Java source line #2025	-> byte code offset #27
/*      */     //   Java source line #2026	-> byte code offset #31
/*      */     //   Java source line #2025	-> byte code offset #43
/*      */     //   Java source line #2026	-> byte code offset #48
/*      */     //   Java source line #2029	-> byte code offset #59
/*      */     // Local variable table:
/*      */     //   start	length	slot	name	signature
/*      */     //   0	60	0	this	ELParser
/*      */     //   9	44	1	jjtn000	AstNull
/*      */     //   11	34	2	jjtc000	boolean
/*      */     //   43	15	3	localObject	Object
/*      */     // Exception table:
/*      */     //   from	to	target	type
/*      */     //   20	27	43	finally
/*      */   }
/*      */   
/*      */   public final void enable_tracing() {}
/*      */   
/*      */   public final void disable_tracing() {}
/*      */ }


/* Location:              C:\Users\ikatwal\Downloads\bullet-zone-server-2.0.jar!\BOOT-INF\lib\tomcat-embed-el-8.5.27.jar!\org\apache\el\parser\ELParser.class
 * Java compiler version: 7 (51.0)
 * JD-Core Version:       0.7.1
 */